[
    {
        "type": "archive",
        "archive-type": "tar-gzip",
        "url": "https://static.crates.io/crates/adler2/adler2-2.0.1.crate",
        "sha256": "320119579fcad9c21884f5c4861d16174d0e06250625266f50fe6898340abefa",
        "dest": "cargo/vendor/adler2-2.0.1"
    },
    {
        "type": "inline",
        "contents": "{\"package\": \"320119579fcad9c21884f5c4861d16174d0e06250625266f50fe6898340abefa\", \"files\": {}}",
        "dest": "cargo/vendor/adler2-2.0.1",
        "dest-filename": ".cargo-checksum.json"
    },
    {
        "type": "archive",
        "archive-type": "tar-gzip",
        "url": "https://static.crates.io/crates/aho-corasick/aho-corasick-1.1.3.crate",
        "sha256": "8e60d3430d3a69478ad0993f19238d2df97c507009a52b3c10addcd7f6bcb916",
        "dest": "cargo/vendor/aho-corasick-1.1.3"
    },
    {
        "type": "inline",
        "contents": "{\"package\": \"8e60d3430d3a69478ad0993f19238d2df97c507009a52b3c10addcd7f6bcb916\", \"files\": {}}",
        "dest": "cargo/vendor/aho-corasick-1.1.3",
        "dest-filename": ".cargo-checksum.json"
    },
    {
        "type": "archive",
        "archive-type": "tar-gzip",
        "url": "https://static.crates.io/crates/anyhow/anyhow-1.0.98.crate",
        "sha256": "e16d2d3311acee920a9eb8d33b8cbc1787ce4a264e85f964c2404b969bdcd487",
        "dest": "cargo/vendor/anyhow-1.0.98"
    },
    {
        "type": "inline",
        "contents": "{\"package\": \"e16d2d3311acee920a9eb8d33b8cbc1787ce4a264e85f964c2404b969bdcd487\", \"files\": {}}",
        "dest": "cargo/vendor/anyhow-1.0.98",
        "dest-filename": ".cargo-checksum.json"
    },
    {
        "type": "archive",
        "archive-type": "tar-gzip",
        "url": "https://static.crates.io/crates/arbitrary/arbitrary-1.4.1.crate",
        "sha256": "dde20b3d026af13f561bdd0f15edf01fc734f0dafcedbaf42bba506a9517f223",
        "dest": "cargo/vendor/arbitrary-1.4.1"
    },
    {
        "type": "inline",
        "contents": "{\"package\": \"dde20b3d026af13f561bdd0f15edf01fc734f0dafcedbaf42bba506a9517f223\", \"files\": {}}",
        "dest": "cargo/vendor/arbitrary-1.4.1",
        "dest-filename": ".cargo-checksum.json"
    },
    {
        "type": "archive",
        "archive-type": "tar-gzip",
        "url": "https://static.crates.io/crates/autocfg/autocfg-1.4.0.crate",
        "sha256": "ace50bade8e6234aa140d9a2f552bbee1db4d353f69b8217bc503490fc1a9f26",
        "dest": "cargo/vendor/autocfg-1.4.0"
    },
    {
        "type": "inline",
        "contents": "{\"package\": \"ace50bade8e6234aa140d9a2f552bbee1db4d353f69b8217bc503490fc1a9f26\", \"files\": {}}",
        "dest": "cargo/vendor/autocfg-1.4.0",
        "dest-filename": ".cargo-checksum.json"
    },
    {
        "type": "archive",
        "archive-type": "tar-gzip",
        "url": "https://static.crates.io/crates/bitflags/bitflags-2.9.0.crate",
        "sha256": "5c8214115b7bf84099f1309324e63141d4c5d7cc26862f97a0a857dbefe165bd",
        "dest": "cargo/vendor/bitflags-2.9.0"
    },
    {
        "type": "inline",
        "contents": "{\"package\": \"5c8214115b7bf84099f1309324e63141d4c5d7cc26862f97a0a857dbefe165bd\", \"files\": {}}",
        "dest": "cargo/vendor/bitflags-2.9.0",
        "dest-filename": ".cargo-checksum.json"
    },
    {
        "type": "archive",
        "archive-type": "tar-gzip",
        "url": "https://static.crates.io/crates/block/block-0.1.6.crate",
        "sha256": "0d8c1fef690941d3e7788d328517591fecc684c084084702d6ff1641e993699a",
        "dest": "cargo/vendor/block-0.1.6"
    },
    {
        "type": "inline",
        "contents": "{\"package\": \"0d8c1fef690941d3e7788d328517591fecc684c084084702d6ff1641e993699a\", \"files\": {}}",
        "dest": "cargo/vendor/block-0.1.6",
        "dest-filename": ".cargo-checksum.json"
    },
    {
        "type": "archive",
        "archive-type": "tar-gzip",
        "url": "https://static.crates.io/crates/bstr/bstr-1.10.0.crate",
        "sha256": "40723b8fb387abc38f4f4a37c09073622e41dd12327033091ef8950659e6dc0c",
        "dest": "cargo/vendor/bstr-1.10.0"
    },
    {
        "type": "inline",
        "contents": "{\"package\": \"40723b8fb387abc38f4f4a37c09073622e41dd12327033091ef8950659e6dc0c\", \"files\": {}}",
        "dest": "cargo/vendor/bstr-1.10.0",
        "dest-filename": ".cargo-checksum.json"
    },
    {
        "type": "archive",
        "archive-type": "tar-gzip",
        "url": "https://static.crates.io/crates/bumpalo/bumpalo-3.16.0.crate",
        "sha256": "79296716171880943b8470b5f8d03aa55eb2e645a4874bdbb28adb49162e012c",
        "dest": "cargo/vendor/bumpalo-3.16.0"
    },
    {
        "type": "inline",
        "contents": "{\"package\": \"79296716171880943b8470b5f8d03aa55eb2e645a4874bdbb28adb49162e012c\", \"files\": {}}",
        "dest": "cargo/vendor/bumpalo-3.16.0",
        "dest-filename": ".cargo-checksum.json"
    },
    {
        "type": "archive",
        "archive-type": "tar-gzip",
        "url": "https://static.crates.io/crates/cairo-rs/cairo-rs-0.21.0.crate",
        "sha256": "f6466a563dea2e99f59f6ffbb749fd0bdf75764f5e6e93976b5e7bd73c4c9efb",
        "dest": "cargo/vendor/cairo-rs-0.21.0"
    },
    {
        "type": "inline",
        "contents": "{\"package\": \"f6466a563dea2e99f59f6ffbb749fd0bdf75764f5e6e93976b5e7bd73c4c9efb\", \"files\": {}}",
        "dest": "cargo/vendor/cairo-rs-0.21.0",
        "dest-filename": ".cargo-checksum.json"
    },
    {
        "type": "archive",
        "archive-type": "tar-gzip",
        "url": "https://static.crates.io/crates/cairo-sys-rs/cairo-sys-rs-0.21.0.crate",
        "sha256": "cab7e9f13c802625aad1ad2b4ae3989f4ce9339ff388f335a6f109f9338705e2",
        "dest": "cargo/vendor/cairo-sys-rs-0.21.0"
    },
    {
        "type": "inline",
        "contents": "{\"package\": \"cab7e9f13c802625aad1ad2b4ae3989f4ce9339ff388f335a6f109f9338705e2\", \"files\": {}}",
        "dest": "cargo/vendor/cairo-sys-rs-0.21.0",
        "dest-filename": ".cargo-checksum.json"
    },
    {
        "type": "archive",
        "archive-type": "tar-gzip",
        "url": "https://static.crates.io/crates/cc/cc-1.1.28.crate",
        "sha256": "2e80e3b6a3ab07840e1cae9b0666a63970dc28e8ed5ffbcdacbfc760c281bfc1",
        "dest": "cargo/vendor/cc-1.1.28"
    },
    {
        "type": "inline",
        "contents": "{\"package\": \"2e80e3b6a3ab07840e1cae9b0666a63970dc28e8ed5ffbcdacbfc760c281bfc1\", \"files\": {}}",
        "dest": "cargo/vendor/cc-1.1.28",
        "dest-filename": ".cargo-checksum.json"
    },
    {
        "type": "archive",
        "archive-type": "tar-gzip",
        "url": "https://static.crates.io/crates/cfg-expr/cfg-expr-0.17.2.crate",
        "sha256": "8d4ba6e40bd1184518716a6e1a781bf9160e286d219ccdb8ab2612e74cfe4789",
        "dest": "cargo/vendor/cfg-expr-0.17.2"
    },
    {
        "type": "inline",
        "contents": "{\"package\": \"8d4ba6e40bd1184518716a6e1a781bf9160e286d219ccdb8ab2612e74cfe4789\", \"files\": {}}",
        "dest": "cargo/vendor/cfg-expr-0.17.2",
        "dest-filename": ".cargo-checksum.json"
    },
    {
        "type": "archive",
        "archive-type": "tar-gzip",
        "url": "https://static.crates.io/crates/cfg-if/cfg-if-1.0.0.crate",
        "sha256": "baf1de4339761588bc0619e3cbc0120ee582ebb74b53b4efbf79117bd2da40fd",
        "dest": "cargo/vendor/cfg-if-1.0.0"
    },
    {
        "type": "inline",
        "contents": "{\"package\": \"baf1de4339761588bc0619e3cbc0120ee582ebb74b53b4efbf79117bd2da40fd\", \"files\": {}}",
        "dest": "cargo/vendor/cfg-if-1.0.0",
        "dest-filename": ".cargo-checksum.json"
    },
    {
        "type": "archive",
        "archive-type": "tar-gzip",
        "url": "https://static.crates.io/crates/crc32fast/crc32fast-1.4.2.crate",
        "sha256": "a97769d94ddab943e4510d138150169a2758b5ef3eb191a9ee688de3e23ef7b3",
        "dest": "cargo/vendor/crc32fast-1.4.2"
    },
    {
        "type": "inline",
        "contents": "{\"package\": \"a97769d94ddab943e4510d138150169a2758b5ef3eb191a9ee688de3e23ef7b3\", \"files\": {}}",
        "dest": "cargo/vendor/crc32fast-1.4.2",
        "dest-filename": ".cargo-checksum.json"
    },
    {
        "type": "archive",
        "archive-type": "tar-gzip",
        "url": "https://static.crates.io/crates/crossbeam-deque/crossbeam-deque-0.8.5.crate",
        "sha256": "613f8cc01fe9cf1a3eb3d7f488fd2fa8388403e97039e2f73692932e291a770d",
        "dest": "cargo/vendor/crossbeam-deque-0.8.5"
    },
    {
        "type": "inline",
        "contents": "{\"package\": \"613f8cc01fe9cf1a3eb3d7f488fd2fa8388403e97039e2f73692932e291a770d\", \"files\": {}}",
        "dest": "cargo/vendor/crossbeam-deque-0.8.5",
        "dest-filename": ".cargo-checksum.json"
    },
    {
        "type": "archive",
        "archive-type": "tar-gzip",
        "url": "https://static.crates.io/crates/crossbeam-epoch/crossbeam-epoch-0.9.18.crate",
        "sha256": "5b82ac4a3c2ca9c3460964f020e1402edd5753411d7737aa39c3714ad1b5420e",
        "dest": "cargo/vendor/crossbeam-epoch-0.9.18"
    },
    {
        "type": "inline",
        "contents": "{\"package\": \"5b82ac4a3c2ca9c3460964f020e1402edd5753411d7737aa39c3714ad1b5420e\", \"files\": {}}",
        "dest": "cargo/vendor/crossbeam-epoch-0.9.18",
        "dest-filename": ".cargo-checksum.json"
    },
    {
        "type": "archive",
        "archive-type": "tar-gzip",
        "url": "https://static.crates.io/crates/crossbeam-utils/crossbeam-utils-0.8.20.crate",
        "sha256": "22ec99545bb0ed0ea7bb9b8e1e9122ea386ff8a48c0922e43f36d45ab09e0e80",
        "dest": "cargo/vendor/crossbeam-utils-0.8.20"
    },
    {
        "type": "inline",
        "contents": "{\"package\": \"22ec99545bb0ed0ea7bb9b8e1e9122ea386ff8a48c0922e43f36d45ab09e0e80\", \"files\": {}}",
        "dest": "cargo/vendor/crossbeam-utils-0.8.20",
        "dest-filename": ".cargo-checksum.json"
    },
    {
        "type": "archive",
        "archive-type": "tar-gzip",
        "url": "https://static.crates.io/crates/derive_arbitrary/derive_arbitrary-1.4.1.crate",
        "sha256": "30542c1ad912e0e3d22a1935c290e12e8a29d704a420177a31faad4a601a0800",
        "dest": "cargo/vendor/derive_arbitrary-1.4.1"
    },
    {
        "type": "inline",
        "contents": "{\"package\": \"30542c1ad912e0e3d22a1935c290e12e8a29d704a420177a31faad4a601a0800\", \"files\": {}}",
        "dest": "cargo/vendor/derive_arbitrary-1.4.1",
        "dest-filename": ".cargo-checksum.json"
    },
    {
        "type": "archive",
        "archive-type": "tar-gzip",
        "url": "https://static.crates.io/crates/encoding_rs/encoding_rs-0.8.34.crate",
        "sha256": "b45de904aa0b010bce2ab45264d0631681847fa7b6f2eaa7dab7619943bc4f59",
        "dest": "cargo/vendor/encoding_rs-0.8.34"
    },
    {
        "type": "inline",
        "contents": "{\"package\": \"b45de904aa0b010bce2ab45264d0631681847fa7b6f2eaa7dab7619943bc4f59\", \"files\": {}}",
        "dest": "cargo/vendor/encoding_rs-0.8.34",
        "dest-filename": ".cargo-checksum.json"
    },
    {
        "type": "archive",
        "archive-type": "tar-gzip",
        "url": "https://static.crates.io/crates/encoding_rs_io/encoding_rs_io-0.1.7.crate",
        "sha256": "1cc3c5651fb62ab8aa3103998dade57efdd028544bd300516baa31840c252a83",
        "dest": "cargo/vendor/encoding_rs_io-0.1.7"
    },
    {
        "type": "inline",
        "contents": "{\"package\": \"1cc3c5651fb62ab8aa3103998dade57efdd028544bd300516baa31840c252a83\", \"files\": {}}",
        "dest": "cargo/vendor/encoding_rs_io-0.1.7",
        "dest-filename": ".cargo-checksum.json"
    },
    {
        "type": "archive",
        "archive-type": "tar-gzip",
        "url": "https://static.crates.io/crates/env_filter/env_filter-0.1.3.crate",
        "sha256": "186e05a59d4c50738528153b83b0b0194d3a29507dfec16eccd4b342903397d0",
        "dest": "cargo/vendor/env_filter-0.1.3"
    },
    {
        "type": "inline",
        "contents": "{\"package\": \"186e05a59d4c50738528153b83b0b0194d3a29507dfec16eccd4b342903397d0\", \"files\": {}}",
        "dest": "cargo/vendor/env_filter-0.1.3",
        "dest-filename": ".cargo-checksum.json"
    },
    {
        "type": "archive",
        "archive-type": "tar-gzip",
        "url": "https://static.crates.io/crates/env_logger/env_logger-0.11.8.crate",
        "sha256": "13c863f0904021b108aa8b2f55046443e6b1ebde8fd4a15c399893aae4fa069f",
        "dest": "cargo/vendor/env_logger-0.11.8"
    },
    {
        "type": "inline",
        "contents": "{\"package\": \"13c863f0904021b108aa8b2f55046443e6b1ebde8fd4a15c399893aae4fa069f\", \"files\": {}}",
        "dest": "cargo/vendor/env_logger-0.11.8",
        "dest-filename": ".cargo-checksum.json"
    },
    {
        "type": "archive",
        "archive-type": "tar-gzip",
        "url": "https://static.crates.io/crates/equivalent/equivalent-1.0.2.crate",
        "sha256": "877a4ace8713b0bcf2a4e7eec82529c029f1d0619886d18145fea96c3ffe5c0f",
        "dest": "cargo/vendor/equivalent-1.0.2"
    },
    {
        "type": "inline",
        "contents": "{\"package\": \"877a4ace8713b0bcf2a4e7eec82529c029f1d0619886d18145fea96c3ffe5c0f\", \"files\": {}}",
        "dest": "cargo/vendor/equivalent-1.0.2",
        "dest-filename": ".cargo-checksum.json"
    },
    {
        "type": "archive",
        "archive-type": "tar-gzip",
        "url": "https://static.crates.io/crates/field-offset/field-offset-0.3.6.crate",
        "sha256": "38e2275cc4e4fc009b0669731a1e5ab7ebf11f469eaede2bab9309a5b4d6057f",
        "dest": "cargo/vendor/field-offset-0.3.6"
    },
    {
        "type": "inline",
        "contents": "{\"package\": \"38e2275cc4e4fc009b0669731a1e5ab7ebf11f469eaede2bab9309a5b4d6057f\", \"files\": {}}",
        "dest": "cargo/vendor/field-offset-0.3.6",
        "dest-filename": ".cargo-checksum.json"
    },
    {
        "type": "archive",
        "archive-type": "tar-gzip",
        "url": "https://static.crates.io/crates/flate2/flate2-1.1.2.crate",
        "sha256": "4a3d7db9596fecd151c5f638c0ee5d5bd487b6e0ea232e5dc96d5250f6f94b1d",
        "dest": "cargo/vendor/flate2-1.1.2"
    },
    {
        "type": "inline",
        "contents": "{\"package\": \"4a3d7db9596fecd151c5f638c0ee5d5bd487b6e0ea232e5dc96d5250f6f94b1d\", \"files\": {}}",
        "dest": "cargo/vendor/flate2-1.1.2",
        "dest-filename": ".cargo-checksum.json"
    },
    {
        "type": "archive",
        "archive-type": "tar-gzip",
        "url": "https://static.crates.io/crates/flume/flume-0.11.1.crate",
        "sha256": "da0e4dd2a88388a1f4ccc7c9ce104604dab68d9f408dc34cd45823d5a9069095",
        "dest": "cargo/vendor/flume-0.11.1"
    },
    {
        "type": "inline",
        "contents": "{\"package\": \"da0e4dd2a88388a1f4ccc7c9ce104604dab68d9f408dc34cd45823d5a9069095\", \"files\": {}}",
        "dest": "cargo/vendor/flume-0.11.1",
        "dest-filename": ".cargo-checksum.json"
    },
    {
        "type": "archive",
        "archive-type": "tar-gzip",
        "url": "https://static.crates.io/crates/futures-channel/futures-channel-0.3.31.crate",
        "sha256": "2dff15bf788c671c1934e366d07e30c1814a8ef514e1af724a602e8a2fbe1b10",
        "dest": "cargo/vendor/futures-channel-0.3.31"
    },
    {
        "type": "inline",
        "contents": "{\"package\": \"2dff15bf788c671c1934e366d07e30c1814a8ef514e1af724a602e8a2fbe1b10\", \"files\": {}}",
        "dest": "cargo/vendor/futures-channel-0.3.31",
        "dest-filename": ".cargo-checksum.json"
    },
    {
        "type": "archive",
        "archive-type": "tar-gzip",
        "url": "https://static.crates.io/crates/futures-core/futures-core-0.3.31.crate",
        "sha256": "05f29059c0c2090612e8d742178b0580d2dc940c837851ad723096f87af6663e",
        "dest": "cargo/vendor/futures-core-0.3.31"
    },
    {
        "type": "inline",
        "contents": "{\"package\": \"05f29059c0c2090612e8d742178b0580d2dc940c837851ad723096f87af6663e\", \"files\": {}}",
        "dest": "cargo/vendor/futures-core-0.3.31",
        "dest-filename": ".cargo-checksum.json"
    },
    {
        "type": "archive",
        "archive-type": "tar-gzip",
        "url": "https://static.crates.io/crates/futures-executor/futures-executor-0.3.31.crate",
        "sha256": "1e28d1d997f585e54aebc3f97d39e72338912123a67330d723fdbb564d646c9f",
        "dest": "cargo/vendor/futures-executor-0.3.31"
    },
    {
        "type": "inline",
        "contents": "{\"package\": \"1e28d1d997f585e54aebc3f97d39e72338912123a67330d723fdbb564d646c9f\", \"files\": {}}",
        "dest": "cargo/vendor/futures-executor-0.3.31",
        "dest-filename": ".cargo-checksum.json"
    },
    {
        "type": "archive",
        "archive-type": "tar-gzip",
        "url": "https://static.crates.io/crates/futures-io/futures-io-0.3.31.crate",
        "sha256": "9e5c1b78ca4aae1ac06c48a526a655760685149f0d465d21f37abfe57ce075c6",
        "dest": "cargo/vendor/futures-io-0.3.31"
    },
    {
        "type": "inline",
        "contents": "{\"package\": \"9e5c1b78ca4aae1ac06c48a526a655760685149f0d465d21f37abfe57ce075c6\", \"files\": {}}",
        "dest": "cargo/vendor/futures-io-0.3.31",
        "dest-filename": ".cargo-checksum.json"
    },
    {
        "type": "archive",
        "archive-type": "tar-gzip",
        "url": "https://static.crates.io/crates/futures-macro/futures-macro-0.3.31.crate",
        "sha256": "162ee34ebcb7c64a8abebc059ce0fee27c2262618d7b60ed8faf72fef13c3650",
        "dest": "cargo/vendor/futures-macro-0.3.31"
    },
    {
        "type": "inline",
        "contents": "{\"package\": \"162ee34ebcb7c64a8abebc059ce0fee27c2262618d7b60ed8faf72fef13c3650\", \"files\": {}}",
        "dest": "cargo/vendor/futures-macro-0.3.31",
        "dest-filename": ".cargo-checksum.json"
    },
    {
        "type": "archive",
        "archive-type": "tar-gzip",
        "url": "https://static.crates.io/crates/futures-sink/futures-sink-0.3.31.crate",
        "sha256": "e575fab7d1e0dcb8d0c7bcf9a63ee213816ab51902e6d244a95819acacf1d4f7",
        "dest": "cargo/vendor/futures-sink-0.3.31"
    },
    {
        "type": "inline",
        "contents": "{\"package\": \"e575fab7d1e0dcb8d0c7bcf9a63ee213816ab51902e6d244a95819acacf1d4f7\", \"files\": {}}",
        "dest": "cargo/vendor/futures-sink-0.3.31",
        "dest-filename": ".cargo-checksum.json"
    },
    {
        "type": "archive",
        "archive-type": "tar-gzip",
        "url": "https://static.crates.io/crates/futures-task/futures-task-0.3.31.crate",
        "sha256": "f90f7dce0722e95104fcb095585910c0977252f286e354b5e3bd38902cd99988",
        "dest": "cargo/vendor/futures-task-0.3.31"
    },
    {
        "type": "inline",
        "contents": "{\"package\": \"f90f7dce0722e95104fcb095585910c0977252f286e354b5e3bd38902cd99988\", \"files\": {}}",
        "dest": "cargo/vendor/futures-task-0.3.31",
        "dest-filename": ".cargo-checksum.json"
    },
    {
        "type": "archive",
        "archive-type": "tar-gzip",
        "url": "https://static.crates.io/crates/futures-util/futures-util-0.3.31.crate",
        "sha256": "9fa08315bb612088cc391249efdc3bc77536f16c91f6cf495e6fbe85b20a4a81",
        "dest": "cargo/vendor/futures-util-0.3.31"
    },
    {
        "type": "inline",
        "contents": "{\"package\": \"9fa08315bb612088cc391249efdc3bc77536f16c91f6cf495e6fbe85b20a4a81\", \"files\": {}}",
        "dest": "cargo/vendor/futures-util-0.3.31",
        "dest-filename": ".cargo-checksum.json"
    },
    {
        "type": "archive",
        "archive-type": "tar-gzip",
        "url": "https://static.crates.io/crates/gdk-pixbuf/gdk-pixbuf-0.21.0.crate",
        "sha256": "688dc7eaf551dbac1f5b11d000d089c3db29feb25562455f47c1a2080cc60bda",
        "dest": "cargo/vendor/gdk-pixbuf-0.21.0"
    },
    {
        "type": "inline",
        "contents": "{\"package\": \"688dc7eaf551dbac1f5b11d000d089c3db29feb25562455f47c1a2080cc60bda\", \"files\": {}}",
        "dest": "cargo/vendor/gdk-pixbuf-0.21.0",
        "dest-filename": ".cargo-checksum.json"
    },
    {
        "type": "archive",
        "archive-type": "tar-gzip",
        "url": "https://static.crates.io/crates/gdk-pixbuf-sys/gdk-pixbuf-sys-0.21.0.crate",
        "sha256": "5af1823d3d1cb72616873ba0a593bd440eb92da700fdfb047505a21ee3ec3e10",
        "dest": "cargo/vendor/gdk-pixbuf-sys-0.21.0"
    },
    {
        "type": "inline",
        "contents": "{\"package\": \"5af1823d3d1cb72616873ba0a593bd440eb92da700fdfb047505a21ee3ec3e10\", \"files\": {}}",
        "dest": "cargo/vendor/gdk-pixbuf-sys-0.21.0",
        "dest-filename": ".cargo-checksum.json"
    },
    {
        "type": "archive",
        "archive-type": "tar-gzip",
        "url": "https://static.crates.io/crates/gdk4/gdk4-0.10.0.crate",
        "sha256": "0a67b064d2f35e649232455c7724f56f977555d2608c43300eabc530eaa4e359",
        "dest": "cargo/vendor/gdk4-0.10.0"
    },
    {
        "type": "inline",
        "contents": "{\"package\": \"0a67b064d2f35e649232455c7724f56f977555d2608c43300eabc530eaa4e359\", \"files\": {}}",
        "dest": "cargo/vendor/gdk4-0.10.0",
        "dest-filename": ".cargo-checksum.json"
    },
    {
        "type": "archive",
        "archive-type": "tar-gzip",
        "url": "https://static.crates.io/crates/gdk4-sys/gdk4-sys-0.10.0.crate",
        "sha256": "2edbda0d879eb85317bdb49a3da591ed70a804a10776e358ef416be38c6db2c5",
        "dest": "cargo/vendor/gdk4-sys-0.10.0"
    },
    {
        "type": "inline",
        "contents": "{\"package\": \"2edbda0d879eb85317bdb49a3da591ed70a804a10776e358ef416be38c6db2c5\", \"files\": {}}",
        "dest": "cargo/vendor/gdk4-sys-0.10.0",
        "dest-filename": ".cargo-checksum.json"
    },
    {
        "type": "archive",
        "archive-type": "tar-gzip",
        "url": "https://static.crates.io/crates/getrandom/getrandom-0.2.15.crate",
        "sha256": "c4567c8db10ae91089c99af84c68c38da3ec2f087c3f82960bcdbf3656b6f4d7",
        "dest": "cargo/vendor/getrandom-0.2.15"
    },
    {
        "type": "inline",
        "contents": "{\"package\": \"c4567c8db10ae91089c99af84c68c38da3ec2f087c3f82960bcdbf3656b6f4d7\", \"files\": {}}",
        "dest": "cargo/vendor/getrandom-0.2.15",
        "dest-filename": ".cargo-checksum.json"
    },
    {
        "type": "archive",
        "archive-type": "tar-gzip",
        "url": "https://static.crates.io/crates/gettext-rs/gettext-rs-0.7.2.crate",
        "sha256": "a44e92f7dc08430aca7ed55de161253a22276dfd69c5526e5c5e95d1f7cf338a",
        "dest": "cargo/vendor/gettext-rs-0.7.2"
    },
    {
        "type": "inline",
        "contents": "{\"package\": \"a44e92f7dc08430aca7ed55de161253a22276dfd69c5526e5c5e95d1f7cf338a\", \"files\": {}}",
        "dest": "cargo/vendor/gettext-rs-0.7.2",
        "dest-filename": ".cargo-checksum.json"
    },
    {
        "type": "archive",
        "archive-type": "tar-gzip",
        "url": "https://static.crates.io/crates/gettext-sys/gettext-sys-0.21.4.crate",
        "sha256": "f7b8797f28f2dabfbe2caadb6db4f7fd739e251b5ede0a2ba49e506071edcf67",
        "dest": "cargo/vendor/gettext-sys-0.21.4"
    },
    {
        "type": "inline",
        "contents": "{\"package\": \"f7b8797f28f2dabfbe2caadb6db4f7fd739e251b5ede0a2ba49e506071edcf67\", \"files\": {}}",
        "dest": "cargo/vendor/gettext-sys-0.21.4",
        "dest-filename": ".cargo-checksum.json"
    },
    {
        "type": "archive",
        "archive-type": "tar-gzip",
        "url": "https://static.crates.io/crates/gio/gio-0.21.0.crate",
        "sha256": "273d64c833fbbf7cd86c4cdced893c5d3f2f5d6aeb30fd0c30d172456ce8be2e",
        "dest": "cargo/vendor/gio-0.21.0"
    },
    {
        "type": "inline",
        "contents": "{\"package\": \"273d64c833fbbf7cd86c4cdced893c5d3f2f5d6aeb30fd0c30d172456ce8be2e\", \"files\": {}}",
        "dest": "cargo/vendor/gio-0.21.0",
        "dest-filename": ".cargo-checksum.json"
    },
    {
        "type": "archive",
        "archive-type": "tar-gzip",
        "url": "https://static.crates.io/crates/gio-sys/gio-sys-0.21.0.crate",
        "sha256": "2c8130f5810a839d74afc3a929c34a700bf194972bb034f2ecfe639682dd13cc",
        "dest": "cargo/vendor/gio-sys-0.21.0"
    },
    {
        "type": "inline",
        "contents": "{\"package\": \"2c8130f5810a839d74afc3a929c34a700bf194972bb034f2ecfe639682dd13cc\", \"files\": {}}",
        "dest": "cargo/vendor/gio-sys-0.21.0",
        "dest-filename": ".cargo-checksum.json"
    },
    {
        "type": "archive",
        "archive-type": "tar-gzip",
        "url": "https://static.crates.io/crates/glib/glib-0.21.0.crate",
        "sha256": "690e8bcf8a819b5911d6ae79879226191d01253a4f602748072603defd5b9553",
        "dest": "cargo/vendor/glib-0.21.0"
    },
    {
        "type": "inline",
        "contents": "{\"package\": \"690e8bcf8a819b5911d6ae79879226191d01253a4f602748072603defd5b9553\", \"files\": {}}",
        "dest": "cargo/vendor/glib-0.21.0",
        "dest-filename": ".cargo-checksum.json"
    },
    {
        "type": "archive",
        "archive-type": "tar-gzip",
        "url": "https://static.crates.io/crates/glib-macros/glib-macros-0.21.0.crate",
        "sha256": "e772291ebea14c28eb11bb75741f62f4a4894f25e60ce80100797b6b010ef0f9",
        "dest": "cargo/vendor/glib-macros-0.21.0"
    },
    {
        "type": "inline",
        "contents": "{\"package\": \"e772291ebea14c28eb11bb75741f62f4a4894f25e60ce80100797b6b010ef0f9\", \"files\": {}}",
        "dest": "cargo/vendor/glib-macros-0.21.0",
        "dest-filename": ".cargo-checksum.json"
    },
    {
        "type": "archive",
        "archive-type": "tar-gzip",
        "url": "https://static.crates.io/crates/glib-sys/glib-sys-0.21.0.crate",
        "sha256": "4b2be4c74454fb4a6bd3328320737d0fa3d6939e2d570f5d846da00cb222f6a0",
        "dest": "cargo/vendor/glib-sys-0.21.0"
    },
    {
        "type": "inline",
        "contents": "{\"package\": \"4b2be4c74454fb4a6bd3328320737d0fa3d6939e2d570f5d846da00cb222f6a0\", \"files\": {}}",
        "dest": "cargo/vendor/glib-sys-0.21.0",
        "dest-filename": ".cargo-checksum.json"
    },
    {
        "type": "archive",
        "archive-type": "tar-gzip",
        "url": "https://static.crates.io/crates/glob/glob-0.3.2.crate",
        "sha256": "a8d1add55171497b4705a648c6b583acafb01d58050a51727785f0b2c8e0a2b2",
        "dest": "cargo/vendor/glob-0.3.2"
    },
    {
        "type": "inline",
        "contents": "{\"package\": \"a8d1add55171497b4705a648c6b583acafb01d58050a51727785f0b2c8e0a2b2\", \"files\": {}}",
        "dest": "cargo/vendor/glob-0.3.2",
        "dest-filename": ".cargo-checksum.json"
    },
    {
        "type": "archive",
        "archive-type": "tar-gzip",
        "url": "https://static.crates.io/crates/globset/globset-0.4.15.crate",
        "sha256": "15f1ce686646e7f1e19bf7d5533fe443a45dbfb990e00629110797578b42fb19",
        "dest": "cargo/vendor/globset-0.4.15"
    },
    {
        "type": "inline",
        "contents": "{\"package\": \"15f1ce686646e7f1e19bf7d5533fe443a45dbfb990e00629110797578b42fb19\", \"files\": {}}",
        "dest": "cargo/vendor/globset-0.4.15",
        "dest-filename": ".cargo-checksum.json"
    },
    {
        "type": "archive",
        "archive-type": "tar-gzip",
        "url": "https://static.crates.io/crates/gobject-sys/gobject-sys-0.21.0.crate",
        "sha256": "ab318a786f9abd49d388013b9161fa0ef8218ea6118ee7111c95e62186f7d31f",
        "dest": "cargo/vendor/gobject-sys-0.21.0"
    },
    {
        "type": "inline",
        "contents": "{\"package\": \"ab318a786f9abd49d388013b9161fa0ef8218ea6118ee7111c95e62186f7d31f\", \"files\": {}}",
        "dest": "cargo/vendor/gobject-sys-0.21.0",
        "dest-filename": ".cargo-checksum.json"
    },
    {
        "type": "archive",
        "archive-type": "tar-gzip",
        "url": "https://static.crates.io/crates/graphene-rs/graphene-rs-0.21.0.crate",
        "sha256": "0487f78e8a772ec89020458fbabadd1332bc1e3236ca1c63ef1d61afd4e5f2cc",
        "dest": "cargo/vendor/graphene-rs-0.21.0"
    },
    {
        "type": "inline",
        "contents": "{\"package\": \"0487f78e8a772ec89020458fbabadd1332bc1e3236ca1c63ef1d61afd4e5f2cc\", \"files\": {}}",
        "dest": "cargo/vendor/graphene-rs-0.21.0",
        "dest-filename": ".cargo-checksum.json"
    },
    {
        "type": "archive",
        "archive-type": "tar-gzip",
        "url": "https://static.crates.io/crates/graphene-sys/graphene-sys-0.21.0.crate",
        "sha256": "270cefb6b270fcb2ef9708c3a35c0e25c2e831dac28d75c4f87e5ad3540c9543",
        "dest": "cargo/vendor/graphene-sys-0.21.0"
    },
    {
        "type": "inline",
        "contents": "{\"package\": \"270cefb6b270fcb2ef9708c3a35c0e25c2e831dac28d75c4f87e5ad3540c9543\", \"files\": {}}",
        "dest": "cargo/vendor/graphene-sys-0.21.0",
        "dest-filename": ".cargo-checksum.json"
    },
    {
        "type": "archive",
        "archive-type": "tar-gzip",
        "url": "https://static.crates.io/crates/grep/grep-0.3.2.crate",
        "sha256": "308ae749734e28d749a86f33212c7b756748568ce332f970ac1d9cd8531f32e6",
        "dest": "cargo/vendor/grep-0.3.2"
    },
    {
        "type": "inline",
        "contents": "{\"package\": \"308ae749734e28d749a86f33212c7b756748568ce332f970ac1d9cd8531f32e6\", \"files\": {}}",
        "dest": "cargo/vendor/grep-0.3.2",
        "dest-filename": ".cargo-checksum.json"
    },
    {
        "type": "archive",
        "archive-type": "tar-gzip",
        "url": "https://static.crates.io/crates/grep-cli/grep-cli-0.1.11.crate",
        "sha256": "47f1288f0e06f279f84926fa4c17e3fcd2a22b357927a82f2777f7be26e4cec0",
        "dest": "cargo/vendor/grep-cli-0.1.11"
    },
    {
        "type": "inline",
        "contents": "{\"package\": \"47f1288f0e06f279f84926fa4c17e3fcd2a22b357927a82f2777f7be26e4cec0\", \"files\": {}}",
        "dest": "cargo/vendor/grep-cli-0.1.11",
        "dest-filename": ".cargo-checksum.json"
    },
    {
        "type": "archive",
        "archive-type": "tar-gzip",
        "url": "https://static.crates.io/crates/grep-matcher/grep-matcher-0.1.7.crate",
        "sha256": "47a3141a10a43acfedc7c98a60a834d7ba00dfe7bec9071cbfc19b55b292ac02",
        "dest": "cargo/vendor/grep-matcher-0.1.7"
    },
    {
        "type": "inline",
        "contents": "{\"package\": \"47a3141a10a43acfedc7c98a60a834d7ba00dfe7bec9071cbfc19b55b292ac02\", \"files\": {}}",
        "dest": "cargo/vendor/grep-matcher-0.1.7",
        "dest-filename": ".cargo-checksum.json"
    },
    {
        "type": "archive",
        "archive-type": "tar-gzip",
        "url": "https://static.crates.io/crates/grep-printer/grep-printer-0.2.2.crate",
        "sha256": "c112110ae4a891aa4d83ab82ecf734b307497d066f437686175e83fbd4e013fe",
        "dest": "cargo/vendor/grep-printer-0.2.2"
    },
    {
        "type": "inline",
        "contents": "{\"package\": \"c112110ae4a891aa4d83ab82ecf734b307497d066f437686175e83fbd4e013fe\", \"files\": {}}",
        "dest": "cargo/vendor/grep-printer-0.2.2",
        "dest-filename": ".cargo-checksum.json"
    },
    {
        "type": "archive",
        "archive-type": "tar-gzip",
        "url": "https://static.crates.io/crates/grep-regex/grep-regex-0.1.13.crate",
        "sha256": "9edd147c7e3296e7a26bd3a81345ce849557d5a8e48ed88f736074e760f91f7e",
        "dest": "cargo/vendor/grep-regex-0.1.13"
    },
    {
        "type": "inline",
        "contents": "{\"package\": \"9edd147c7e3296e7a26bd3a81345ce849557d5a8e48ed88f736074e760f91f7e\", \"files\": {}}",
        "dest": "cargo/vendor/grep-regex-0.1.13",
        "dest-filename": ".cargo-checksum.json"
    },
    {
        "type": "archive",
        "archive-type": "tar-gzip",
        "url": "https://static.crates.io/crates/grep-searcher/grep-searcher-0.1.14.crate",
        "sha256": "b9b6c14b3fc2e0a107d6604d3231dec0509e691e62447104bc385a46a7892cda",
        "dest": "cargo/vendor/grep-searcher-0.1.14"
    },
    {
        "type": "inline",
        "contents": "{\"package\": \"b9b6c14b3fc2e0a107d6604d3231dec0509e691e62447104bc385a46a7892cda\", \"files\": {}}",
        "dest": "cargo/vendor/grep-searcher-0.1.14",
        "dest-filename": ".cargo-checksum.json"
    },
    {
        "type": "archive",
        "archive-type": "tar-gzip",
        "url": "https://static.crates.io/crates/gsk4/gsk4-0.10.0.crate",
        "sha256": "d5dbe33ceed6fc20def67c03d36e532f5a4a569ae437ae015a7146094f31e10c",
        "dest": "cargo/vendor/gsk4-0.10.0"
    },
    {
        "type": "inline",
        "contents": "{\"package\": \"d5dbe33ceed6fc20def67c03d36e532f5a4a569ae437ae015a7146094f31e10c\", \"files\": {}}",
        "dest": "cargo/vendor/gsk4-0.10.0",
        "dest-filename": ".cargo-checksum.json"
    },
    {
        "type": "archive",
        "archive-type": "tar-gzip",
        "url": "https://static.crates.io/crates/gsk4-sys/gsk4-sys-0.10.0.crate",
        "sha256": "8d76011d55dd19fde16ffdedee08877ae6ec942818cfa7bc08a91259bc0b9fc9",
        "dest": "cargo/vendor/gsk4-sys-0.10.0"
    },
    {
        "type": "inline",
        "contents": "{\"package\": \"8d76011d55dd19fde16ffdedee08877ae6ec942818cfa7bc08a91259bc0b9fc9\", \"files\": {}}",
        "dest": "cargo/vendor/gsk4-sys-0.10.0",
        "dest-filename": ".cargo-checksum.json"
    },
    {
        "type": "archive",
        "archive-type": "tar-gzip",
        "url": "https://static.crates.io/crates/gtk4/gtk4-0.10.0.crate",
        "sha256": "938d68ad43080ad5ee710c30d467c1bc022ee5947856f593855691d726305b3e",
        "dest": "cargo/vendor/gtk4-0.10.0"
    },
    {
        "type": "inline",
        "contents": "{\"package\": \"938d68ad43080ad5ee710c30d467c1bc022ee5947856f593855691d726305b3e\", \"files\": {}}",
        "dest": "cargo/vendor/gtk4-0.10.0",
        "dest-filename": ".cargo-checksum.json"
    },
    {
        "type": "archive",
        "archive-type": "tar-gzip",
        "url": "https://static.crates.io/crates/gtk4-macros/gtk4-macros-0.10.0.crate",
        "sha256": "0912d2068695633002b92c5966edc108b2e4f54b58c509d1eeddd4cbceb7315c",
        "dest": "cargo/vendor/gtk4-macros-0.10.0"
    },
    {
        "type": "inline",
        "contents": "{\"package\": \"0912d2068695633002b92c5966edc108b2e4f54b58c509d1eeddd4cbceb7315c\", \"files\": {}}",
        "dest": "cargo/vendor/gtk4-macros-0.10.0",
        "dest-filename": ".cargo-checksum.json"
    },
    {
        "type": "archive",
        "archive-type": "tar-gzip",
        "url": "https://static.crates.io/crates/gtk4-sys/gtk4-sys-0.10.0.crate",
        "sha256": "a923bdcf00e46723801162de24432cbce38a6810e0178a2d0b6dd4ecc26a1c74",
        "dest": "cargo/vendor/gtk4-sys-0.10.0"
    },
    {
        "type": "inline",
        "contents": "{\"package\": \"a923bdcf00e46723801162de24432cbce38a6810e0178a2d0b6dd4ecc26a1c74\", \"files\": {}}",
        "dest": "cargo/vendor/gtk4-sys-0.10.0",
        "dest-filename": ".cargo-checksum.json"
    },
    {
        "type": "archive",
        "archive-type": "tar-gzip",
        "url": "https://static.crates.io/crates/hashbrown/hashbrown-0.15.3.crate",
        "sha256": "84b26c544d002229e640969970a2e74021aadf6e2f96372b9c58eff97de08eb3",
        "dest": "cargo/vendor/hashbrown-0.15.3"
    },
    {
        "type": "inline",
        "contents": "{\"package\": \"84b26c544d002229e640969970a2e74021aadf6e2f96372b9c58eff97de08eb3\", \"files\": {}}",
        "dest": "cargo/vendor/hashbrown-0.15.3",
        "dest-filename": ".cargo-checksum.json"
    },
    {
        "type": "archive",
        "archive-type": "tar-gzip",
        "url": "https://static.crates.io/crates/heck/heck-0.5.0.crate",
        "sha256": "2304e00983f87ffb38b55b444b5e3b60a884b5d30c0fca7d82fe33449bbe55ea",
        "dest": "cargo/vendor/heck-0.5.0"
    },
    {
        "type": "inline",
        "contents": "{\"package\": \"2304e00983f87ffb38b55b444b5e3b60a884b5d30c0fca7d82fe33449bbe55ea\", \"files\": {}}",
        "dest": "cargo/vendor/heck-0.5.0",
        "dest-filename": ".cargo-checksum.json"
    },
    {
        "type": "archive",
        "archive-type": "tar-gzip",
        "url": "https://static.crates.io/crates/ignore/ignore-0.4.23.crate",
        "sha256": "6d89fd380afde86567dfba715db065673989d6253f42b88179abd3eae47bda4b",
        "dest": "cargo/vendor/ignore-0.4.23"
    },
    {
        "type": "inline",
        "contents": "{\"package\": \"6d89fd380afde86567dfba715db065673989d6253f42b88179abd3eae47bda4b\", \"files\": {}}",
        "dest": "cargo/vendor/ignore-0.4.23",
        "dest-filename": ".cargo-checksum.json"
    },
    {
        "type": "archive",
        "archive-type": "tar-gzip",
        "url": "https://static.crates.io/crates/indexmap/indexmap-2.9.0.crate",
        "sha256": "cea70ddb795996207ad57735b50c5982d8844f38ba9ee5f1aedcfb708a2aa11e",
        "dest": "cargo/vendor/indexmap-2.9.0"
    },
    {
        "type": "inline",
        "contents": "{\"package\": \"cea70ddb795996207ad57735b50c5982d8844f38ba9ee5f1aedcfb708a2aa11e\", \"files\": {}}",
        "dest": "cargo/vendor/indexmap-2.9.0",
        "dest-filename": ".cargo-checksum.json"
    },
    {
        "type": "archive",
        "archive-type": "tar-gzip",
        "url": "https://static.crates.io/crates/itoa/itoa-1.0.11.crate",
        "sha256": "49f1f14873335454500d59611f1cf4a4b0f786f9ac11f4312a78e4cf2566695b",
        "dest": "cargo/vendor/itoa-1.0.11"
    },
    {
        "type": "inline",
        "contents": "{\"package\": \"49f1f14873335454500d59611f1cf4a4b0f786f9ac11f4312a78e4cf2566695b\", \"files\": {}}",
        "dest": "cargo/vendor/itoa-1.0.11",
        "dest-filename": ".cargo-checksum.json"
    },
    {
        "type": "archive",
        "archive-type": "tar-gzip",
        "url": "https://static.crates.io/crates/js-sys/js-sys-0.3.70.crate",
        "sha256": "1868808506b929d7b0cfa8f75951347aa71bb21144b7791bae35d9bccfcfe37a",
        "dest": "cargo/vendor/js-sys-0.3.70"
    },
    {
        "type": "inline",
        "contents": "{\"package\": \"1868808506b929d7b0cfa8f75951347aa71bb21144b7791bae35d9bccfcfe37a\", \"files\": {}}",
        "dest": "cargo/vendor/js-sys-0.3.70",
        "dest-filename": ".cargo-checksum.json"
    },
    {
        "type": "archive",
        "archive-type": "tar-gzip",
        "url": "https://static.crates.io/crates/lazy_static/lazy_static-1.5.0.crate",
        "sha256": "bbd2bcb4c963f2ddae06a2efc7e9f3591312473c50c6685e1f298068316e66fe",
        "dest": "cargo/vendor/lazy_static-1.5.0"
    },
    {
        "type": "inline",
        "contents": "{\"package\": \"bbd2bcb4c963f2ddae06a2efc7e9f3591312473c50c6685e1f298068316e66fe\", \"files\": {}}",
        "dest": "cargo/vendor/lazy_static-1.5.0",
        "dest-filename": ".cargo-checksum.json"
    },
    {
        "type": "archive",
        "archive-type": "tar-gzip",
        "url": "https://static.crates.io/crates/libadwaita/libadwaita-0.8.0.crate",
        "sha256": "4df6715d1257bd8c093295b77a276ed129d73543b10304fec5829ced5d5b7c41",
        "dest": "cargo/vendor/libadwaita-0.8.0"
    },
    {
        "type": "inline",
        "contents": "{\"package\": \"4df6715d1257bd8c093295b77a276ed129d73543b10304fec5829ced5d5b7c41\", \"files\": {}}",
        "dest": "cargo/vendor/libadwaita-0.8.0",
        "dest-filename": ".cargo-checksum.json"
    },
    {
        "type": "archive",
        "archive-type": "tar-gzip",
        "url": "https://static.crates.io/crates/libadwaita-sys/libadwaita-sys-0.8.0.crate",
        "sha256": "fdf8950090cc180250cdb1ff859a39748feeda7a53a9f28ead3a17a14cc37ae2",
        "dest": "cargo/vendor/libadwaita-sys-0.8.0"
    },
    {
        "type": "inline",
        "contents": "{\"package\": \"fdf8950090cc180250cdb1ff859a39748feeda7a53a9f28ead3a17a14cc37ae2\", \"files\": {}}",
        "dest": "cargo/vendor/libadwaita-sys-0.8.0",
        "dest-filename": ".cargo-checksum.json"
    },
    {
        "type": "archive",
        "archive-type": "tar-gzip",
        "url": "https://static.crates.io/crates/libc/libc-0.2.172.crate",
        "sha256": "d750af042f7ef4f724306de029d18836c26c1765a54a6a3f094cbd23a7267ffa",
        "dest": "cargo/vendor/libc-0.2.172"
    },
    {
        "type": "inline",
        "contents": "{\"package\": \"d750af042f7ef4f724306de029d18836c26c1765a54a6a3f094cbd23a7267ffa\", \"files\": {}}",
        "dest": "cargo/vendor/libc-0.2.172",
        "dest-filename": ".cargo-checksum.json"
    },
    {
        "type": "archive",
        "archive-type": "tar-gzip",
        "url": "https://static.crates.io/crates/libz-rs-sys/libz-rs-sys-0.5.1.crate",
        "sha256": "172a788537a2221661b480fee8dc5f96c580eb34fa88764d3205dc356c7e4221",
        "dest": "cargo/vendor/libz-rs-sys-0.5.1"
    },
    {
        "type": "inline",
        "contents": "{\"package\": \"172a788537a2221661b480fee8dc5f96c580eb34fa88764d3205dc356c7e4221\", \"files\": {}}",
        "dest": "cargo/vendor/libz-rs-sys-0.5.1",
        "dest-filename": ".cargo-checksum.json"
    },
    {
        "type": "archive",
        "archive-type": "tar-gzip",
        "url": "https://static.crates.io/crates/locale_config/locale_config-0.3.0.crate",
        "sha256": "08d2c35b16f4483f6c26f0e4e9550717a2f6575bcd6f12a53ff0c490a94a6934",
        "dest": "cargo/vendor/locale_config-0.3.0"
    },
    {
        "type": "inline",
        "contents": "{\"package\": \"08d2c35b16f4483f6c26f0e4e9550717a2f6575bcd6f12a53ff0c490a94a6934\", \"files\": {}}",
        "dest": "cargo/vendor/locale_config-0.3.0",
        "dest-filename": ".cargo-checksum.json"
    },
    {
        "type": "archive",
        "archive-type": "tar-gzip",
        "url": "https://static.crates.io/crates/lock_api/lock_api-0.4.12.crate",
        "sha256": "07af8b9cdd281b7915f413fa73f29ebd5d55d0d3f0155584dade1ff18cea1b17",
        "dest": "cargo/vendor/lock_api-0.4.12"
    },
    {
        "type": "inline",
        "contents": "{\"package\": \"07af8b9cdd281b7915f413fa73f29ebd5d55d0d3f0155584dade1ff18cea1b17\", \"files\": {}}",
        "dest": "cargo/vendor/lock_api-0.4.12",
        "dest-filename": ".cargo-checksum.json"
    },
    {
        "type": "archive",
        "archive-type": "tar-gzip",
        "url": "https://static.crates.io/crates/lockfree-object-pool/lockfree-object-pool-0.1.6.crate",
        "sha256": "9374ef4228402d4b7e403e5838cb880d9ee663314b0a900d5a6aabf0c213552e",
        "dest": "cargo/vendor/lockfree-object-pool-0.1.6"
    },
    {
        "type": "inline",
        "contents": "{\"package\": \"9374ef4228402d4b7e403e5838cb880d9ee663314b0a900d5a6aabf0c213552e\", \"files\": {}}",
        "dest": "cargo/vendor/lockfree-object-pool-0.1.6",
        "dest-filename": ".cargo-checksum.json"
    },
    {
        "type": "archive",
        "archive-type": "tar-gzip",
        "url": "https://static.crates.io/crates/log/log-0.4.27.crate",
        "sha256": "13dc2df351e3202783a1fe0d44375f7295ffb4049267b0f3018346dc122a1d94",
        "dest": "cargo/vendor/log-0.4.27"
    },
    {
        "type": "inline",
        "contents": "{\"package\": \"13dc2df351e3202783a1fe0d44375f7295ffb4049267b0f3018346dc122a1d94\", \"files\": {}}",
        "dest": "cargo/vendor/log-0.4.27",
        "dest-filename": ".cargo-checksum.json"
    },
    {
        "type": "archive",
        "archive-type": "tar-gzip",
        "url": "https://static.crates.io/crates/malloc_buf/malloc_buf-0.0.6.crate",
        "sha256": "62bb907fe88d54d8d9ce32a3cceab4218ed2f6b7d35617cafe9adf84e43919cb",
        "dest": "cargo/vendor/malloc_buf-0.0.6"
    },
    {
        "type": "inline",
        "contents": "{\"package\": \"62bb907fe88d54d8d9ce32a3cceab4218ed2f6b7d35617cafe9adf84e43919cb\", \"files\": {}}",
        "dest": "cargo/vendor/malloc_buf-0.0.6",
        "dest-filename": ".cargo-checksum.json"
    },
    {
        "type": "archive",
        "archive-type": "tar-gzip",
        "url": "https://static.crates.io/crates/memchr/memchr-2.7.5.crate",
        "sha256": "32a282da65faaf38286cf3be983213fcf1d2e2a58700e808f83f4ea9a4804bc0",
        "dest": "cargo/vendor/memchr-2.7.5"
    },
    {
        "type": "inline",
        "contents": "{\"package\": \"32a282da65faaf38286cf3be983213fcf1d2e2a58700e808f83f4ea9a4804bc0\", \"files\": {}}",
        "dest": "cargo/vendor/memchr-2.7.5",
        "dest-filename": ".cargo-checksum.json"
    },
    {
        "type": "archive",
        "archive-type": "tar-gzip",
        "url": "https://static.crates.io/crates/memmap2/memmap2-0.9.5.crate",
        "sha256": "fd3f7eed9d3848f8b98834af67102b720745c4ec028fcd0aa0239277e7de374f",
        "dest": "cargo/vendor/memmap2-0.9.5"
    },
    {
        "type": "inline",
        "contents": "{\"package\": \"fd3f7eed9d3848f8b98834af67102b720745c4ec028fcd0aa0239277e7de374f\", \"files\": {}}",
        "dest": "cargo/vendor/memmap2-0.9.5",
        "dest-filename": ".cargo-checksum.json"
    },
    {
        "type": "archive",
        "archive-type": "tar-gzip",
        "url": "https://static.crates.io/crates/memoffset/memoffset-0.9.1.crate",
        "sha256": "488016bfae457b036d996092f6cb448677611ce4449e970ceaf42695203f218a",
        "dest": "cargo/vendor/memoffset-0.9.1"
    },
    {
        "type": "inline",
        "contents": "{\"package\": \"488016bfae457b036d996092f6cb448677611ce4449e970ceaf42695203f218a\", \"files\": {}}",
        "dest": "cargo/vendor/memoffset-0.9.1",
        "dest-filename": ".cargo-checksum.json"
    },
    {
        "type": "archive",
        "archive-type": "tar-gzip",
        "url": "https://static.crates.io/crates/miniz_oxide/miniz_oxide-0.8.9.crate",
        "sha256": "1fa76a2c86f704bdb222d66965fb3d63269ce38518b83cb0575fca855ebb6316",
        "dest": "cargo/vendor/miniz_oxide-0.8.9"
    },
    {
        "type": "inline",
        "contents": "{\"package\": \"1fa76a2c86f704bdb222d66965fb3d63269ce38518b83cb0575fca855ebb6316\", \"files\": {}}",
        "dest": "cargo/vendor/miniz_oxide-0.8.9",
        "dest-filename": ".cargo-checksum.json"
    },
    {
        "type": "archive",
        "archive-type": "tar-gzip",
        "url": "https://static.crates.io/crates/nanorand/nanorand-0.7.0.crate",
        "sha256": "6a51313c5820b0b02bd422f4b44776fbf47961755c74ce64afc73bfad10226c3",
        "dest": "cargo/vendor/nanorand-0.7.0"
    },
    {
        "type": "inline",
        "contents": "{\"package\": \"6a51313c5820b0b02bd422f4b44776fbf47961755c74ce64afc73bfad10226c3\", \"files\": {}}",
        "dest": "cargo/vendor/nanorand-0.7.0",
        "dest-filename": ".cargo-checksum.json"
    },
    {
        "type": "archive",
        "archive-type": "tar-gzip",
        "url": "https://static.crates.io/crates/objc/objc-0.2.7.crate",
        "sha256": "915b1b472bc21c53464d6c8461c9d3af805ba1ef837e1cac254428f4a77177b1",
        "dest": "cargo/vendor/objc-0.2.7"
    },
    {
        "type": "inline",
        "contents": "{\"package\": \"915b1b472bc21c53464d6c8461c9d3af805ba1ef837e1cac254428f4a77177b1\", \"files\": {}}",
        "dest": "cargo/vendor/objc-0.2.7",
        "dest-filename": ".cargo-checksum.json"
    },
    {
        "type": "archive",
        "archive-type": "tar-gzip",
        "url": "https://static.crates.io/crates/objc-foundation/objc-foundation-0.1.1.crate",
        "sha256": "1add1b659e36c9607c7aab864a76c7a4c2760cd0cd2e120f3fb8b952c7e22bf9",
        "dest": "cargo/vendor/objc-foundation-0.1.1"
    },
    {
        "type": "inline",
        "contents": "{\"package\": \"1add1b659e36c9607c7aab864a76c7a4c2760cd0cd2e120f3fb8b952c7e22bf9\", \"files\": {}}",
        "dest": "cargo/vendor/objc-foundation-0.1.1",
        "dest-filename": ".cargo-checksum.json"
    },
    {
        "type": "archive",
        "archive-type": "tar-gzip",
        "url": "https://static.crates.io/crates/objc_id/objc_id-0.1.1.crate",
        "sha256": "c92d4ddb4bd7b50d730c215ff871754d0da6b2178849f8a2a2ab69712d0c073b",
        "dest": "cargo/vendor/objc_id-0.1.1"
    },
    {
        "type": "inline",
        "contents": "{\"package\": \"c92d4ddb4bd7b50d730c215ff871754d0da6b2178849f8a2a2ab69712d0c073b\", \"files\": {}}",
        "dest": "cargo/vendor/objc_id-0.1.1",
        "dest-filename": ".cargo-checksum.json"
    },
    {
        "type": "archive",
        "archive-type": "tar-gzip",
        "url": "https://static.crates.io/crates/once_cell/once_cell-1.20.2.crate",
        "sha256": "1261fe7e33c73b354eab43b1273a57c8f967d0391e80353e51f764ac02cf6775",
        "dest": "cargo/vendor/once_cell-1.20.2"
    },
    {
        "type": "inline",
        "contents": "{\"package\": \"1261fe7e33c73b354eab43b1273a57c8f967d0391e80353e51f764ac02cf6775\", \"files\": {}}",
        "dest": "cargo/vendor/once_cell-1.20.2",
        "dest-filename": ".cargo-checksum.json"
    },
    {
        "type": "archive",
        "archive-type": "tar-gzip",
        "url": "https://static.crates.io/crates/pango/pango-0.21.0.crate",
        "sha256": "2d4803f086c4f49163c31ac14db162112a22401c116435080e4be8678c507d61",
        "dest": "cargo/vendor/pango-0.21.0"
    },
    {
        "type": "inline",
        "contents": "{\"package\": \"2d4803f086c4f49163c31ac14db162112a22401c116435080e4be8678c507d61\", \"files\": {}}",
        "dest": "cargo/vendor/pango-0.21.0",
        "dest-filename": ".cargo-checksum.json"
    },
    {
        "type": "archive",
        "archive-type": "tar-gzip",
        "url": "https://static.crates.io/crates/pango-sys/pango-sys-0.21.0.crate",
        "sha256": "66872b3cfd328ad6d1a4f89ebd5357119bd4c592a4ddbb8f6bc2386f8ce7b898",
        "dest": "cargo/vendor/pango-sys-0.21.0"
    },
    {
        "type": "inline",
        "contents": "{\"package\": \"66872b3cfd328ad6d1a4f89ebd5357119bd4c592a4ddbb8f6bc2386f8ce7b898\", \"files\": {}}",
        "dest": "cargo/vendor/pango-sys-0.21.0",
        "dest-filename": ".cargo-checksum.json"
    },
    {
        "type": "archive",
        "archive-type": "tar-gzip",
        "url": "https://static.crates.io/crates/pin-project-lite/pin-project-lite-0.2.16.crate",
        "sha256": "3b3cff922bd51709b605d9ead9aa71031d81447142d828eb4a6eba76fe619f9b",
        "dest": "cargo/vendor/pin-project-lite-0.2.16"
    },
    {
        "type": "inline",
        "contents": "{\"package\": \"3b3cff922bd51709b605d9ead9aa71031d81447142d828eb4a6eba76fe619f9b\", \"files\": {}}",
        "dest": "cargo/vendor/pin-project-lite-0.2.16",
        "dest-filename": ".cargo-checksum.json"
    },
    {
        "type": "archive",
        "archive-type": "tar-gzip",
        "url": "https://static.crates.io/crates/pin-utils/pin-utils-0.1.0.crate",
        "sha256": "8b870d8c151b6f2fb93e84a13146138f05d02ed11c7e7c54f8826aaaf7c9f184",
        "dest": "cargo/vendor/pin-utils-0.1.0"
    },
    {
        "type": "inline",
        "contents": "{\"package\": \"8b870d8c151b6f2fb93e84a13146138f05d02ed11c7e7c54f8826aaaf7c9f184\", \"files\": {}}",
        "dest": "cargo/vendor/pin-utils-0.1.0",
        "dest-filename": ".cargo-checksum.json"
    },
    {
        "type": "archive",
        "archive-type": "tar-gzip",
        "url": "https://static.crates.io/crates/pkg-config/pkg-config-0.3.32.crate",
        "sha256": "7edddbd0b52d732b21ad9a5fab5c704c14cd949e5e9a1ec5929a24fded1b904c",
        "dest": "cargo/vendor/pkg-config-0.3.32"
    },
    {
        "type": "inline",
        "contents": "{\"package\": \"7edddbd0b52d732b21ad9a5fab5c704c14cd949e5e9a1ec5929a24fded1b904c\", \"files\": {}}",
        "dest": "cargo/vendor/pkg-config-0.3.32",
        "dest-filename": ".cargo-checksum.json"
    },
    {
        "type": "archive",
        "archive-type": "tar-gzip",
        "url": "https://static.crates.io/crates/poppler-rs/poppler-rs-0.25.0.crate",
        "sha256": "f654ec8b83bca9adb0ea7e62194a1e5767a094d282d77630ff0ddb2edbc30139",
        "dest": "cargo/vendor/poppler-rs-0.25.0"
    },
    {
        "type": "inline",
        "contents": "{\"package\": \"f654ec8b83bca9adb0ea7e62194a1e5767a094d282d77630ff0ddb2edbc30139\", \"files\": {}}",
        "dest": "cargo/vendor/poppler-rs-0.25.0",
        "dest-filename": ".cargo-checksum.json"
    },
    {
        "type": "archive",
        "archive-type": "tar-gzip",
        "url": "https://static.crates.io/crates/poppler-sys-rs/poppler-sys-rs-0.25.0.crate",
        "sha256": "7f59d8616943cf71be2a33d866dee973eaaa3e507eb21eb102c6424f773ea6ad",
        "dest": "cargo/vendor/poppler-sys-rs-0.25.0"
    },
    {
        "type": "inline",
        "contents": "{\"package\": \"7f59d8616943cf71be2a33d866dee973eaaa3e507eb21eb102c6424f773ea6ad\", \"files\": {}}",
        "dest": "cargo/vendor/poppler-sys-rs-0.25.0",
        "dest-filename": ".cargo-checksum.json"
    },
    {
        "type": "archive",
        "archive-type": "tar-gzip",
        "url": "https://static.crates.io/crates/proc-macro-crate/proc-macro-crate-3.3.0.crate",
        "sha256": "edce586971a4dfaa28950c6f18ed55e0406c1ab88bbce2c6f6293a7aaba73d35",
        "dest": "cargo/vendor/proc-macro-crate-3.3.0"
    },
    {
        "type": "inline",
        "contents": "{\"package\": \"edce586971a4dfaa28950c6f18ed55e0406c1ab88bbce2c6f6293a7aaba73d35\", \"files\": {}}",
        "dest": "cargo/vendor/proc-macro-crate-3.3.0",
        "dest-filename": ".cargo-checksum.json"
    },
    {
        "type": "archive",
        "archive-type": "tar-gzip",
        "url": "https://static.crates.io/crates/proc-macro2/proc-macro2-1.0.95.crate",
        "sha256": "02b3e5e68a3a1a02aad3ec490a98007cbc13c37cbe84a3cd7b8e406d76e7f778",
        "dest": "cargo/vendor/proc-macro2-1.0.95"
    },
    {
        "type": "inline",
        "contents": "{\"package\": \"02b3e5e68a3a1a02aad3ec490a98007cbc13c37cbe84a3cd7b8e406d76e7f778\", \"files\": {}}",
        "dest": "cargo/vendor/proc-macro2-1.0.95",
        "dest-filename": ".cargo-checksum.json"
    },
    {
        "type": "archive",
        "archive-type": "tar-gzip",
        "url": "https://static.crates.io/crates/quick-xml/quick-xml-0.38.0.crate",
        "sha256": "8927b0664f5c5a98265138b7e3f90aa19a6b21353182469ace36d4ac527b7b1b",
        "dest": "cargo/vendor/quick-xml-0.38.0"
    },
    {
        "type": "inline",
        "contents": "{\"package\": \"8927b0664f5c5a98265138b7e3f90aa19a6b21353182469ace36d4ac527b7b1b\", \"files\": {}}",
        "dest": "cargo/vendor/quick-xml-0.38.0",
        "dest-filename": ".cargo-checksum.json"
    },
    {
        "type": "archive",
        "archive-type": "tar-gzip",
        "url": "https://static.crates.io/crates/quote/quote-1.0.40.crate",
        "sha256": "1885c039570dc00dcb4ff087a89e185fd56bae234ddc7f056a945bf36467248d",
        "dest": "cargo/vendor/quote-1.0.40"
    },
    {
        "type": "inline",
        "contents": "{\"package\": \"1885c039570dc00dcb4ff087a89e185fd56bae234ddc7f056a945bf36467248d\", \"files\": {}}",
        "dest": "cargo/vendor/quote-1.0.40",
        "dest-filename": ".cargo-checksum.json"
    },
    {
        "type": "archive",
        "archive-type": "tar-gzip",
        "url": "https://static.crates.io/crates/regex/regex-1.11.0.crate",
        "sha256": "38200e5ee88914975b69f657f0801b6f6dccafd44fd9326302a4aaeecfacb1d8",
        "dest": "cargo/vendor/regex-1.11.0"
    },
    {
        "type": "inline",
        "contents": "{\"package\": \"38200e5ee88914975b69f657f0801b6f6dccafd44fd9326302a4aaeecfacb1d8\", \"files\": {}}",
        "dest": "cargo/vendor/regex-1.11.0",
        "dest-filename": ".cargo-checksum.json"
    },
    {
        "type": "archive",
        "archive-type": "tar-gzip",
        "url": "https://static.crates.io/crates/regex-automata/regex-automata-0.4.8.crate",
        "sha256": "368758f23274712b504848e9d5a6f010445cc8b87a7cdb4d7cbee666c1288da3",
        "dest": "cargo/vendor/regex-automata-0.4.8"
    },
    {
        "type": "inline",
        "contents": "{\"package\": \"368758f23274712b504848e9d5a6f010445cc8b87a7cdb4d7cbee666c1288da3\", \"files\": {}}",
        "dest": "cargo/vendor/regex-automata-0.4.8",
        "dest-filename": ".cargo-checksum.json"
    },
    {
        "type": "archive",
        "archive-type": "tar-gzip",
        "url": "https://static.crates.io/crates/regex-syntax/regex-syntax-0.8.5.crate",
        "sha256": "2b15c43186be67a4fd63bee50d0303afffcef381492ebe2c5d87f324e1b8815c",
        "dest": "cargo/vendor/regex-syntax-0.8.5"
    },
    {
        "type": "inline",
        "contents": "{\"package\": \"2b15c43186be67a4fd63bee50d0303afffcef381492ebe2c5d87f324e1b8815c\", \"files\": {}}",
        "dest": "cargo/vendor/regex-syntax-0.8.5",
        "dest-filename": ".cargo-checksum.json"
    },
    {
        "type": "archive",
        "archive-type": "tar-gzip",
        "url": "https://static.crates.io/crates/rustc_version/rustc_version-0.4.1.crate",
        "sha256": "cfcb3a22ef46e85b45de6ee7e79d063319ebb6594faafcf1c225ea92ab6e9b92",
        "dest": "cargo/vendor/rustc_version-0.4.1"
    },
    {
        "type": "inline",
        "contents": "{\"package\": \"cfcb3a22ef46e85b45de6ee7e79d063319ebb6594faafcf1c225ea92ab6e9b92\", \"files\": {}}",
        "dest": "cargo/vendor/rustc_version-0.4.1",
        "dest-filename": ".cargo-checksum.json"
    },
    {
        "type": "archive",
        "archive-type": "tar-gzip",
        "url": "https://static.crates.io/crates/ryu/ryu-1.0.18.crate",
        "sha256": "f3cb5ba0dc43242ce17de99c180e96db90b235b8a9fdc9543c96d2209116bd9f",
        "dest": "cargo/vendor/ryu-1.0.18"
    },
    {
        "type": "inline",
        "contents": "{\"package\": \"f3cb5ba0dc43242ce17de99c180e96db90b235b8a9fdc9543c96d2209116bd9f\", \"files\": {}}",
        "dest": "cargo/vendor/ryu-1.0.18",
        "dest-filename": ".cargo-checksum.json"
    },
    {
        "type": "archive",
        "archive-type": "tar-gzip",
        "url": "https://static.crates.io/crates/same-file/same-file-1.0.6.crate",
        "sha256": "93fc1dc3aaa9bfed95e02e6eadabb4baf7e3078b0bd1b4d7b6b0b68378900502",
        "dest": "cargo/vendor/same-file-1.0.6"
    },
    {
        "type": "inline",
        "contents": "{\"package\": \"93fc1dc3aaa9bfed95e02e6eadabb4baf7e3078b0bd1b4d7b6b0b68378900502\", \"files\": {}}",
        "dest": "cargo/vendor/same-file-1.0.6",
        "dest-filename": ".cargo-checksum.json"
    },
    {
        "type": "archive",
        "archive-type": "tar-gzip",
        "url": "https://static.crates.io/crates/scopeguard/scopeguard-1.2.0.crate",
        "sha256": "94143f37725109f92c262ed2cf5e59bce7498c01bcc1502d7b9afe439a4e9f49",
        "dest": "cargo/vendor/scopeguard-1.2.0"
    },
    {
        "type": "inline",
        "contents": "{\"package\": \"94143f37725109f92c262ed2cf5e59bce7498c01bcc1502d7b9afe439a4e9f49\", \"files\": {}}",
        "dest": "cargo/vendor/scopeguard-1.2.0",
        "dest-filename": ".cargo-checksum.json"
    },
    {
        "type": "archive",
        "archive-type": "tar-gzip",
        "url": "https://static.crates.io/crates/semver/semver-1.0.26.crate",
        "sha256": "56e6fa9c48d24d85fb3de5ad847117517440f6beceb7798af16b4a87d616b8d0",
        "dest": "cargo/vendor/semver-1.0.26"
    },
    {
        "type": "inline",
        "contents": "{\"package\": \"56e6fa9c48d24d85fb3de5ad847117517440f6beceb7798af16b4a87d616b8d0\", \"files\": {}}",
        "dest": "cargo/vendor/semver-1.0.26",
        "dest-filename": ".cargo-checksum.json"
    },
    {
        "type": "archive",
        "archive-type": "tar-gzip",
        "url": "https://static.crates.io/crates/serde/serde-1.0.219.crate",
        "sha256": "5f0e2c6ed6606019b4e29e69dbaba95b11854410e5347d525002456dbbb786b6",
        "dest": "cargo/vendor/serde-1.0.219"
    },
    {
        "type": "inline",
        "contents": "{\"package\": \"5f0e2c6ed6606019b4e29e69dbaba95b11854410e5347d525002456dbbb786b6\", \"files\": {}}",
        "dest": "cargo/vendor/serde-1.0.219",
        "dest-filename": ".cargo-checksum.json"
    },
    {
        "type": "archive",
        "archive-type": "tar-gzip",
        "url": "https://static.crates.io/crates/serde_derive/serde_derive-1.0.219.crate",
        "sha256": "5b0276cf7f2c73365f7157c8123c21cd9a50fbbd844757af28ca1f5925fc2a00",
        "dest": "cargo/vendor/serde_derive-1.0.219"
    },
    {
        "type": "inline",
        "contents": "{\"package\": \"5b0276cf7f2c73365f7157c8123c21cd9a50fbbd844757af28ca1f5925fc2a00\", \"files\": {}}",
        "dest": "cargo/vendor/serde_derive-1.0.219",
        "dest-filename": ".cargo-checksum.json"
    },
    {
        "type": "archive",
        "archive-type": "tar-gzip",
        "url": "https://static.crates.io/crates/serde_json/serde_json-1.0.128.crate",
        "sha256": "6ff5456707a1de34e7e37f2a6fd3d3f808c318259cbd01ab6377795054b483d8",
        "dest": "cargo/vendor/serde_json-1.0.128"
    },
    {
        "type": "inline",
        "contents": "{\"package\": \"6ff5456707a1de34e7e37f2a6fd3d3f808c318259cbd01ab6377795054b483d8\", \"files\": {}}",
        "dest": "cargo/vendor/serde_json-1.0.128",
        "dest-filename": ".cargo-checksum.json"
    },
    {
        "type": "archive",
        "archive-type": "tar-gzip",
        "url": "https://static.crates.io/crates/serde_spanned/serde_spanned-0.6.8.crate",
        "sha256": "87607cb1398ed59d48732e575a4c28a7a8ebf2454b964fe3f224f2afc07909e1",
        "dest": "cargo/vendor/serde_spanned-0.6.8"
    },
    {
        "type": "inline",
        "contents": "{\"package\": \"87607cb1398ed59d48732e575a4c28a7a8ebf2454b964fe3f224f2afc07909e1\", \"files\": {}}",
        "dest": "cargo/vendor/serde_spanned-0.6.8",
        "dest-filename": ".cargo-checksum.json"
    },
    {
        "type": "archive",
        "archive-type": "tar-gzip",
        "url": "https://static.crates.io/crates/serde_spanned/serde_spanned-1.0.0.crate",
        "sha256": "40734c41988f7306bb04f0ecf60ec0f3f1caa34290e4e8ea471dcd3346483b83",
        "dest": "cargo/vendor/serde_spanned-1.0.0"
    },
    {
        "type": "inline",
        "contents": "{\"package\": \"40734c41988f7306bb04f0ecf60ec0f3f1caa34290e4e8ea471dcd3346483b83\", \"files\": {}}",
        "dest": "cargo/vendor/serde_spanned-1.0.0",
        "dest-filename": ".cargo-checksum.json"
    },
    {
        "type": "archive",
        "archive-type": "tar-gzip",
        "url": "https://static.crates.io/crates/shlex/shlex-1.3.0.crate",
        "sha256": "0fda2ff0d084019ba4d7c6f371c95d8fd75ce3524c3cb8fb653a3023f6323e64",
        "dest": "cargo/vendor/shlex-1.3.0"
    },
    {
        "type": "inline",
        "contents": "{\"package\": \"0fda2ff0d084019ba4d7c6f371c95d8fd75ce3524c3cb8fb653a3023f6323e64\", \"files\": {}}",
        "dest": "cargo/vendor/shlex-1.3.0",
        "dest-filename": ".cargo-checksum.json"
    },
    {
        "type": "archive",
        "archive-type": "tar-gzip",
        "url": "https://static.crates.io/crates/simd-adler32/simd-adler32-0.3.7.crate",
        "sha256": "d66dc143e6b11c1eddc06d5c423cfc97062865baf299914ab64caa38182078fe",
        "dest": "cargo/vendor/simd-adler32-0.3.7"
    },
    {
        "type": "inline",
        "contents": "{\"package\": \"d66dc143e6b11c1eddc06d5c423cfc97062865baf299914ab64caa38182078fe\", \"files\": {}}",
        "dest": "cargo/vendor/simd-adler32-0.3.7",
        "dest-filename": ".cargo-checksum.json"
    },
    {
        "type": "archive",
        "archive-type": "tar-gzip",
        "url": "https://static.crates.io/crates/slab/slab-0.4.9.crate",
        "sha256": "8f92a496fb766b417c996b9c5e57daf2f7ad3b0bebe1ccfca4856390e3d3bb67",
        "dest": "cargo/vendor/slab-0.4.9"
    },
    {
        "type": "inline",
        "contents": "{\"package\": \"8f92a496fb766b417c996b9c5e57daf2f7ad3b0bebe1ccfca4856390e3d3bb67\", \"files\": {}}",
        "dest": "cargo/vendor/slab-0.4.9",
        "dest-filename": ".cargo-checksum.json"
    },
    {
        "type": "archive",
        "archive-type": "tar-gzip",
        "url": "https://static.crates.io/crates/smallvec/smallvec-1.15.0.crate",
        "sha256": "8917285742e9f3e1683f0a9c4e6b57960b7314d0b08d30d1ecd426713ee2eee9",
        "dest": "cargo/vendor/smallvec-1.15.0"
    },
    {
        "type": "inline",
        "contents": "{\"package\": \"8917285742e9f3e1683f0a9c4e6b57960b7314d0b08d30d1ecd426713ee2eee9\", \"files\": {}}",
        "dest": "cargo/vendor/smallvec-1.15.0",
        "dest-filename": ".cargo-checksum.json"
    },
    {
        "type": "archive",
        "archive-type": "tar-gzip",
        "url": "https://static.crates.io/crates/sourceview5/sourceview5-0.10.0.crate",
        "sha256": "6e4acb02162917d7b689c84f4ed710c22302c67c7e61da28a4e8ac548c04442c",
        "dest": "cargo/vendor/sourceview5-0.10.0"
    },
    {
        "type": "inline",
        "contents": "{\"package\": \"6e4acb02162917d7b689c84f4ed710c22302c67c7e61da28a4e8ac548c04442c\", \"files\": {}}",
        "dest": "cargo/vendor/sourceview5-0.10.0",
        "dest-filename": ".cargo-checksum.json"
    },
    {
        "type": "archive",
        "archive-type": "tar-gzip",
        "url": "https://static.crates.io/crates/sourceview5-sys/sourceview5-sys-0.10.1.crate",
        "sha256": "e1c1529de5df2653788828ef71d44b113bb80e496bc17315f4122106bd6eebae",
        "dest": "cargo/vendor/sourceview5-sys-0.10.1"
    },
    {
        "type": "inline",
        "contents": "{\"package\": \"e1c1529de5df2653788828ef71d44b113bb80e496bc17315f4122106bd6eebae\", \"files\": {}}",
        "dest": "cargo/vendor/sourceview5-sys-0.10.1",
        "dest-filename": ".cargo-checksum.json"
    },
    {
        "type": "archive",
        "archive-type": "tar-gzip",
        "url": "https://static.crates.io/crates/spin/spin-0.9.8.crate",
        "sha256": "6980e8d7511241f8acf4aebddbb1ff938df5eebe98691418c4468d0b72a96a67",
        "dest": "cargo/vendor/spin-0.9.8"
    },
    {
        "type": "inline",
        "contents": "{\"package\": \"6980e8d7511241f8acf4aebddbb1ff938df5eebe98691418c4468d0b72a96a67\", \"files\": {}}",
        "dest": "cargo/vendor/spin-0.9.8",
        "dest-filename": ".cargo-checksum.json"
    },
    {
        "type": "archive",
        "archive-type": "tar-gzip",
        "url": "https://static.crates.io/crates/syn/syn-2.0.104.crate",
        "sha256": "17b6f705963418cdb9927482fa304bc562ece2fdd4f616084c50b7023b435a40",
        "dest": "cargo/vendor/syn-2.0.104"
    },
    {
        "type": "inline",
        "contents": "{\"package\": \"17b6f705963418cdb9927482fa304bc562ece2fdd4f616084c50b7023b435a40\", \"files\": {}}",
        "dest": "cargo/vendor/syn-2.0.104",
        "dest-filename": ".cargo-checksum.json"
    },
    {
        "type": "archive",
        "archive-type": "tar-gzip",
        "url": "https://static.crates.io/crates/system-deps/system-deps-7.0.3.crate",
        "sha256": "66d23aaf9f331227789a99e8de4c91bf46703add012bdfd45fdecdfb2975a005",
        "dest": "cargo/vendor/system-deps-7.0.3"
    },
    {
        "type": "inline",
        "contents": "{\"package\": \"66d23aaf9f331227789a99e8de4c91bf46703add012bdfd45fdecdfb2975a005\", \"files\": {}}",
        "dest": "cargo/vendor/system-deps-7.0.3",
        "dest-filename": ".cargo-checksum.json"
    },
    {
        "type": "archive",
        "archive-type": "tar-gzip",
        "url": "https://static.crates.io/crates/target-lexicon/target-lexicon-0.12.16.crate",
        "sha256": "61c41af27dd6d1e27b1b16b489db798443478cef1f06a660c96db617ba5de3b1",
        "dest": "cargo/vendor/target-lexicon-0.12.16"
    },
    {
        "type": "inline",
        "contents": "{\"package\": \"61c41af27dd6d1e27b1b16b489db798443478cef1f06a660c96db617ba5de3b1\", \"files\": {}}",
        "dest": "cargo/vendor/target-lexicon-0.12.16",
        "dest-filename": ".cargo-checksum.json"
    },
    {
        "type": "archive",
        "archive-type": "tar-gzip",
        "url": "https://static.crates.io/crates/temp-dir/temp-dir-0.1.14.crate",
        "sha256": "bc1ee6eef34f12f765cb94725905c6312b6610ab2b0940889cfe58dae7bc3c72",
        "dest": "cargo/vendor/temp-dir-0.1.14"
    },
    {
        "type": "inline",
        "contents": "{\"package\": \"bc1ee6eef34f12f765cb94725905c6312b6610ab2b0940889cfe58dae7bc3c72\", \"files\": {}}",
        "dest": "cargo/vendor/temp-dir-0.1.14",
        "dest-filename": ".cargo-checksum.json"
    },
    {
        "type": "archive",
        "archive-type": "tar-gzip",
        "url": "https://static.crates.io/crates/termcolor/termcolor-1.4.1.crate",
        "sha256": "06794f8f6c5c898b3275aebefa6b8a1cb24cd2c6c79397ab15774837a0bc5755",
        "dest": "cargo/vendor/termcolor-1.4.1"
    },
    {
        "type": "inline",
        "contents": "{\"package\": \"06794f8f6c5c898b3275aebefa6b8a1cb24cd2c6c79397ab15774837a0bc5755\", \"files\": {}}",
        "dest": "cargo/vendor/termcolor-1.4.1",
        "dest-filename": ".cargo-checksum.json"
    },
    {
        "type": "archive",
        "archive-type": "tar-gzip",
        "url": "https://static.crates.io/crates/toml/toml-0.8.22.crate",
        "sha256": "05ae329d1f08c4d17a59bed7ff5b5a769d062e64a62d34a3261b219e62cd5aae",
        "dest": "cargo/vendor/toml-0.8.22"
    },
    {
        "type": "inline",
        "contents": "{\"package\": \"05ae329d1f08c4d17a59bed7ff5b5a769d062e64a62d34a3261b219e62cd5aae\", \"files\": {}}",
        "dest": "cargo/vendor/toml-0.8.22",
        "dest-filename": ".cargo-checksum.json"
    },
    {
        "type": "archive",
        "archive-type": "tar-gzip",
        "url": "https://static.crates.io/crates/toml/toml-0.9.2.crate",
        "sha256": "ed0aee96c12fa71097902e0bb061a5e1ebd766a6636bb605ba401c45c1650eac",
        "dest": "cargo/vendor/toml-0.9.2"
    },
    {
        "type": "inline",
        "contents": "{\"package\": \"ed0aee96c12fa71097902e0bb061a5e1ebd766a6636bb605ba401c45c1650eac\", \"files\": {}}",
        "dest": "cargo/vendor/toml-0.9.2",
        "dest-filename": ".cargo-checksum.json"
    },
    {
        "type": "archive",
        "archive-type": "tar-gzip",
        "url": "https://static.crates.io/crates/toml_datetime/toml_datetime-0.6.9.crate",
        "sha256": "3da5db5a963e24bc68be8b17b6fa82814bb22ee8660f192bb182771d498f09a3",
        "dest": "cargo/vendor/toml_datetime-0.6.9"
    },
    {
        "type": "inline",
        "contents": "{\"package\": \"3da5db5a963e24bc68be8b17b6fa82814bb22ee8660f192bb182771d498f09a3\", \"files\": {}}",
        "dest": "cargo/vendor/toml_datetime-0.6.9",
        "dest-filename": ".cargo-checksum.json"
    },
    {
        "type": "archive",
        "archive-type": "tar-gzip",
        "url": "https://static.crates.io/crates/toml_datetime/toml_datetime-0.7.0.crate",
        "sha256": "bade1c3e902f58d73d3f294cd7f20391c1cb2fbcb643b73566bc773971df91e3",
        "dest": "cargo/vendor/toml_datetime-0.7.0"
    },
    {
        "type": "inline",
        "contents": "{\"package\": \"bade1c3e902f58d73d3f294cd7f20391c1cb2fbcb643b73566bc773971df91e3\", \"files\": {}}",
        "dest": "cargo/vendor/toml_datetime-0.7.0",
        "dest-filename": ".cargo-checksum.json"
    },
    {
        "type": "archive",
        "archive-type": "tar-gzip",
        "url": "https://static.crates.io/crates/toml_edit/toml_edit-0.22.26.crate",
        "sha256": "310068873db2c5b3e7659d2cc35d21855dbafa50d1ce336397c666e3cb08137e",
        "dest": "cargo/vendor/toml_edit-0.22.26"
    },
    {
        "type": "inline",
        "contents": "{\"package\": \"310068873db2c5b3e7659d2cc35d21855dbafa50d1ce336397c666e3cb08137e\", \"files\": {}}",
        "dest": "cargo/vendor/toml_edit-0.22.26",
        "dest-filename": ".cargo-checksum.json"
    },
    {
        "type": "archive",
        "archive-type": "tar-gzip",
        "url": "https://static.crates.io/crates/toml_parser/toml_parser-1.0.1.crate",
        "sha256": "97200572db069e74c512a14117b296ba0a80a30123fbbb5aa1f4a348f639ca30",
        "dest": "cargo/vendor/toml_parser-1.0.1"
    },
    {
        "type": "inline",
        "contents": "{\"package\": \"97200572db069e74c512a14117b296ba0a80a30123fbbb5aa1f4a348f639ca30\", \"files\": {}}",
        "dest": "cargo/vendor/toml_parser-1.0.1",
        "dest-filename": ".cargo-checksum.json"
    },
    {
        "type": "archive",
        "archive-type": "tar-gzip",
        "url": "https://static.crates.io/crates/toml_writer/toml_writer-1.0.2.crate",
        "sha256": "fcc842091f2def52017664b53082ecbbeb5c7731092bad69d2c63050401dfd64",
        "dest": "cargo/vendor/toml_writer-1.0.2"
    },
    {
        "type": "inline",
        "contents": "{\"package\": \"fcc842091f2def52017664b53082ecbbeb5c7731092bad69d2c63050401dfd64\", \"files\": {}}",
        "dest": "cargo/vendor/toml_writer-1.0.2",
        "dest-filename": ".cargo-checksum.json"
    },
    {
        "type": "archive",
        "archive-type": "tar-gzip",
        "url": "https://static.crates.io/crates/unicode-ident/unicode-ident-1.0.18.crate",
        "sha256": "5a5f39404a5da50712a4c1eecf25e90dd62b613502b7e925fd4e4d19b5c96512",
        "dest": "cargo/vendor/unicode-ident-1.0.18"
    },
    {
        "type": "inline",
        "contents": "{\"package\": \"5a5f39404a5da50712a4c1eecf25e90dd62b613502b7e925fd4e4d19b5c96512\", \"files\": {}}",
        "dest": "cargo/vendor/unicode-ident-1.0.18",
        "dest-filename": ".cargo-checksum.json"
    },
    {
        "type": "archive",
        "archive-type": "tar-gzip",
        "url": "https://static.crates.io/crates/version-compare/version-compare-0.2.0.crate",
        "sha256": "852e951cb7832cb45cb1169900d19760cfa39b82bc0ea9c0e5a14ae88411c98b",
        "dest": "cargo/vendor/version-compare-0.2.0"
    },
    {
        "type": "inline",
        "contents": "{\"package\": \"852e951cb7832cb45cb1169900d19760cfa39b82bc0ea9c0e5a14ae88411c98b\", \"files\": {}}",
        "dest": "cargo/vendor/version-compare-0.2.0",
        "dest-filename": ".cargo-checksum.json"
    },
    {
        "type": "archive",
        "archive-type": "tar-gzip",
        "url": "https://static.crates.io/crates/walkdir/walkdir-2.5.0.crate",
        "sha256": "29790946404f91d9c5d06f9874efddea1dc06c5efe94541a7d6863108e3a5e4b",
        "dest": "cargo/vendor/walkdir-2.5.0"
    },
    {
        "type": "inline",
        "contents": "{\"package\": \"29790946404f91d9c5d06f9874efddea1dc06c5efe94541a7d6863108e3a5e4b\", \"files\": {}}",
        "dest": "cargo/vendor/walkdir-2.5.0",
        "dest-filename": ".cargo-checksum.json"
    },
    {
        "type": "archive",
        "archive-type": "tar-gzip",
        "url": "https://static.crates.io/crates/wasi/wasi-0.11.0+wasi-snapshot-preview1.crate",
        "sha256": "9c8d87e72b64a3b4db28d11ce29237c246188f4f51057d65a7eab63b7987e423",
        "dest": "cargo/vendor/wasi-0.11.0+wasi-snapshot-preview1"
    },
    {
        "type": "inline",
        "contents": "{\"package\": \"9c8d87e72b64a3b4db28d11ce29237c246188f4f51057d65a7eab63b7987e423\", \"files\": {}}",
        "dest": "cargo/vendor/wasi-0.11.0+wasi-snapshot-preview1",
        "dest-filename": ".cargo-checksum.json"
    },
    {
        "type": "archive",
        "archive-type": "tar-gzip",
        "url": "https://static.crates.io/crates/wasm-bindgen/wasm-bindgen-0.2.93.crate",
        "sha256": "a82edfc16a6c469f5f44dc7b571814045d60404b55a0ee849f9bcfa2e63dd9b5",
        "dest": "cargo/vendor/wasm-bindgen-0.2.93"
    },
    {
        "type": "inline",
        "contents": "{\"package\": \"a82edfc16a6c469f5f44dc7b571814045d60404b55a0ee849f9bcfa2e63dd9b5\", \"files\": {}}",
        "dest": "cargo/vendor/wasm-bindgen-0.2.93",
        "dest-filename": ".cargo-checksum.json"
    },
    {
        "type": "archive",
        "archive-type": "tar-gzip",
        "url": "https://static.crates.io/crates/wasm-bindgen-backend/wasm-bindgen-backend-0.2.93.crate",
        "sha256": "9de396da306523044d3302746f1208fa71d7532227f15e347e2d93e4145dd77b",
        "dest": "cargo/vendor/wasm-bindgen-backend-0.2.93"
    },
    {
        "type": "inline",
        "contents": "{\"package\": \"9de396da306523044d3302746f1208fa71d7532227f15e347e2d93e4145dd77b\", \"files\": {}}",
        "dest": "cargo/vendor/wasm-bindgen-backend-0.2.93",
        "dest-filename": ".cargo-checksum.json"
    },
    {
        "type": "archive",
        "archive-type": "tar-gzip",
        "url": "https://static.crates.io/crates/wasm-bindgen-macro/wasm-bindgen-macro-0.2.93.crate",
        "sha256": "585c4c91a46b072c92e908d99cb1dcdf95c5218eeb6f3bf1efa991ee7a68cccf",
        "dest": "cargo/vendor/wasm-bindgen-macro-0.2.93"
    },
    {
        "type": "inline",
        "contents": "{\"package\": \"585c4c91a46b072c92e908d99cb1dcdf95c5218eeb6f3bf1efa991ee7a68cccf\", \"files\": {}}",
        "dest": "cargo/vendor/wasm-bindgen-macro-0.2.93",
        "dest-filename": ".cargo-checksum.json"
    },
    {
        "type": "archive",
        "archive-type": "tar-gzip",
        "url": "https://static.crates.io/crates/wasm-bindgen-macro-support/wasm-bindgen-macro-support-0.2.93.crate",
        "sha256": "afc340c74d9005395cf9dd098506f7f44e38f2b4a21c6aaacf9a105ea5e1e836",
        "dest": "cargo/vendor/wasm-bindgen-macro-support-0.2.93"
    },
    {
        "type": "inline",
        "contents": "{\"package\": \"afc340c74d9005395cf9dd098506f7f44e38f2b4a21c6aaacf9a105ea5e1e836\", \"files\": {}}",
        "dest": "cargo/vendor/wasm-bindgen-macro-support-0.2.93",
        "dest-filename": ".cargo-checksum.json"
    },
    {
        "type": "archive",
        "archive-type": "tar-gzip",
        "url": "https://static.crates.io/crates/wasm-bindgen-shared/wasm-bindgen-shared-0.2.93.crate",
        "sha256": "c62a0a307cb4a311d3a07867860911ca130c3494e8c2719593806c08bc5d0484",
        "dest": "cargo/vendor/wasm-bindgen-shared-0.2.93"
    },
    {
        "type": "inline",
        "contents": "{\"package\": \"c62a0a307cb4a311d3a07867860911ca130c3494e8c2719593806c08bc5d0484\", \"files\": {}}",
        "dest": "cargo/vendor/wasm-bindgen-shared-0.2.93",
        "dest-filename": ".cargo-checksum.json"
    },
    {
        "type": "archive",
        "archive-type": "tar-gzip",
        "url": "https://static.crates.io/crates/winapi/winapi-0.3.9.crate",
        "sha256": "5c839a674fcd7a98952e593242ea400abe93992746761e38641405d28b00f419",
        "dest": "cargo/vendor/winapi-0.3.9"
    },
    {
        "type": "inline",
        "contents": "{\"package\": \"5c839a674fcd7a98952e593242ea400abe93992746761e38641405d28b00f419\", \"files\": {}}",
        "dest": "cargo/vendor/winapi-0.3.9",
        "dest-filename": ".cargo-checksum.json"
    },
    {
        "type": "archive",
        "archive-type": "tar-gzip",
        "url": "https://static.crates.io/crates/winapi-i686-pc-windows-gnu/winapi-i686-pc-windows-gnu-0.4.0.crate",
        "sha256": "ac3b87c63620426dd9b991e5ce0329eff545bccbbb34f3be09ff6fb6ab51b7b6",
        "dest": "cargo/vendor/winapi-i686-pc-windows-gnu-0.4.0"
    },
    {
        "type": "inline",
        "contents": "{\"package\": \"ac3b87c63620426dd9b991e5ce0329eff545bccbbb34f3be09ff6fb6ab51b7b6\", \"files\": {}}",
        "dest": "cargo/vendor/winapi-i686-pc-windows-gnu-0.4.0",
        "dest-filename": ".cargo-checksum.json"
    },
    {
        "type": "archive",
        "archive-type": "tar-gzip",
        "url": "https://static.crates.io/crates/winapi-util/winapi-util-0.1.9.crate",
        "sha256": "cf221c93e13a30d793f7645a0e7762c55d169dbb0a49671918a2319d289b10bb",
        "dest": "cargo/vendor/winapi-util-0.1.9"
    },
    {
        "type": "inline",
        "contents": "{\"package\": \"cf221c93e13a30d793f7645a0e7762c55d169dbb0a49671918a2319d289b10bb\", \"files\": {}}",
        "dest": "cargo/vendor/winapi-util-0.1.9",
        "dest-filename": ".cargo-checksum.json"
    },
    {
        "type": "archive",
        "archive-type": "tar-gzip",
        "url": "https://static.crates.io/crates/winapi-x86_64-pc-windows-gnu/winapi-x86_64-pc-windows-gnu-0.4.0.crate",
        "sha256": "712e227841d057c1ee1cd2fb22fa7e5a5461ae8e48fa2ca79ec42cfc1931183f",
        "dest": "cargo/vendor/winapi-x86_64-pc-windows-gnu-0.4.0"
    },
    {
        "type": "inline",
        "contents": "{\"package\": \"712e227841d057c1ee1cd2fb22fa7e5a5461ae8e48fa2ca79ec42cfc1931183f\", \"files\": {}}",
        "dest": "cargo/vendor/winapi-x86_64-pc-windows-gnu-0.4.0",
        "dest-filename": ".cargo-checksum.json"
    },
    {
        "type": "archive",
        "archive-type": "tar-gzip",
        "url": "https://static.crates.io/crates/windows-sys/windows-sys-0.59.0.crate",
        "sha256": "1e38bc4d79ed67fd075bcc251a1c39b32a1776bbe92e5bef1f0bf1f8c531853b",
        "dest": "cargo/vendor/windows-sys-0.59.0"
    },
    {
        "type": "inline",
        "contents": "{\"package\": \"1e38bc4d79ed67fd075bcc251a1c39b32a1776bbe92e5bef1f0bf1f8c531853b\", \"files\": {}}",
        "dest": "cargo/vendor/windows-sys-0.59.0",
        "dest-filename": ".cargo-checksum.json"
    },
    {
        "type": "archive",
        "archive-type": "tar-gzip",
        "url": "https://static.crates.io/crates/windows-targets/windows-targets-0.52.6.crate",
        "sha256": "9b724f72796e036ab90c1021d4780d4d3d648aca59e491e6b98e725b84e99973",
        "dest": "cargo/vendor/windows-targets-0.52.6"
    },
    {
        "type": "inline",
        "contents": "{\"package\": \"9b724f72796e036ab90c1021d4780d4d3d648aca59e491e6b98e725b84e99973\", \"files\": {}}",
        "dest": "cargo/vendor/windows-targets-0.52.6",
        "dest-filename": ".cargo-checksum.json"
    },
    {
        "type": "archive",
        "archive-type": "tar-gzip",
        "url": "https://static.crates.io/crates/windows_aarch64_gnullvm/windows_aarch64_gnullvm-0.52.6.crate",
        "sha256": "32a4622180e7a0ec044bb555404c800bc9fd9ec262ec147edd5989ccd0c02cd3",
        "dest": "cargo/vendor/windows_aarch64_gnullvm-0.52.6"
    },
    {
        "type": "inline",
        "contents": "{\"package\": \"32a4622180e7a0ec044bb555404c800bc9fd9ec262ec147edd5989ccd0c02cd3\", \"files\": {}}",
        "dest": "cargo/vendor/windows_aarch64_gnullvm-0.52.6",
        "dest-filename": ".cargo-checksum.json"
    },
    {
        "type": "archive",
        "archive-type": "tar-gzip",
        "url": "https://static.crates.io/crates/windows_aarch64_msvc/windows_aarch64_msvc-0.52.6.crate",
        "sha256": "09ec2a7bb152e2252b53fa7803150007879548bc709c039df7627cabbd05d469",
        "dest": "cargo/vendor/windows_aarch64_msvc-0.52.6"
    },
    {
        "type": "inline",
        "contents": "{\"package\": \"09ec2a7bb152e2252b53fa7803150007879548bc709c039df7627cabbd05d469\", \"files\": {}}",
        "dest": "cargo/vendor/windows_aarch64_msvc-0.52.6",
        "dest-filename": ".cargo-checksum.json"
    },
    {
        "type": "archive",
        "archive-type": "tar-gzip",
        "url": "https://static.crates.io/crates/windows_i686_gnu/windows_i686_gnu-0.52.6.crate",
        "sha256": "8e9b5ad5ab802e97eb8e295ac6720e509ee4c243f69d781394014ebfe8bbfa0b",
        "dest": "cargo/vendor/windows_i686_gnu-0.52.6"
    },
    {
        "type": "inline",
        "contents": "{\"package\": \"8e9b5ad5ab802e97eb8e295ac6720e509ee4c243f69d781394014ebfe8bbfa0b\", \"files\": {}}",
        "dest": "cargo/vendor/windows_i686_gnu-0.52.6",
        "dest-filename": ".cargo-checksum.json"
    },
    {
        "type": "archive",
        "archive-type": "tar-gzip",
        "url": "https://static.crates.io/crates/windows_i686_gnullvm/windows_i686_gnullvm-0.52.6.crate",
        "sha256": "0eee52d38c090b3caa76c563b86c3a4bd71ef1a819287c19d586d7334ae8ed66",
        "dest": "cargo/vendor/windows_i686_gnullvm-0.52.6"
    },
    {
        "type": "inline",
        "contents": "{\"package\": \"0eee52d38c090b3caa76c563b86c3a4bd71ef1a819287c19d586d7334ae8ed66\", \"files\": {}}",
        "dest": "cargo/vendor/windows_i686_gnullvm-0.52.6",
        "dest-filename": ".cargo-checksum.json"
    },
    {
        "type": "archive",
        "archive-type": "tar-gzip",
        "url": "https://static.crates.io/crates/windows_i686_msvc/windows_i686_msvc-0.52.6.crate",
        "sha256": "240948bc05c5e7c6dabba28bf89d89ffce3e303022809e73deaefe4f6ec56c66",
        "dest": "cargo/vendor/windows_i686_msvc-0.52.6"
    },
    {
        "type": "inline",
        "contents": "{\"package\": \"240948bc05c5e7c6dabba28bf89d89ffce3e303022809e73deaefe4f6ec56c66\", \"files\": {}}",
        "dest": "cargo/vendor/windows_i686_msvc-0.52.6",
        "dest-filename": ".cargo-checksum.json"
    },
    {
        "type": "archive",
        "archive-type": "tar-gzip",
        "url": "https://static.crates.io/crates/windows_x86_64_gnu/windows_x86_64_gnu-0.52.6.crate",
        "sha256": "147a5c80aabfbf0c7d901cb5895d1de30ef2907eb21fbbab29ca94c5b08b1a78",
        "dest": "cargo/vendor/windows_x86_64_gnu-0.52.6"
    },
    {
        "type": "inline",
        "contents": "{\"package\": \"147a5c80aabfbf0c7d901cb5895d1de30ef2907eb21fbbab29ca94c5b08b1a78\", \"files\": {}}",
        "dest": "cargo/vendor/windows_x86_64_gnu-0.52.6",
        "dest-filename": ".cargo-checksum.json"
    },
    {
        "type": "archive",
        "archive-type": "tar-gzip",
        "url": "https://static.crates.io/crates/windows_x86_64_gnullvm/windows_x86_64_gnullvm-0.52.6.crate",
        "sha256": "24d5b23dc417412679681396f2b49f3de8c1473deb516bd34410872eff51ed0d",
        "dest": "cargo/vendor/windows_x86_64_gnullvm-0.52.6"
    },
    {
        "type": "inline",
        "contents": "{\"package\": \"24d5b23dc417412679681396f2b49f3de8c1473deb516bd34410872eff51ed0d\", \"files\": {}}",
        "dest": "cargo/vendor/windows_x86_64_gnullvm-0.52.6",
        "dest-filename": ".cargo-checksum.json"
    },
    {
        "type": "archive",
        "archive-type": "tar-gzip",
        "url": "https://static.crates.io/crates/windows_x86_64_msvc/windows_x86_64_msvc-0.52.6.crate",
        "sha256": "589f6da84c646204747d1270a2a5661ea66ed1cced2631d546fdfb155959f9ec",
        "dest": "cargo/vendor/windows_x86_64_msvc-0.52.6"
    },
    {
        "type": "inline",
        "contents": "{\"package\": \"589f6da84c646204747d1270a2a5661ea66ed1cced2631d546fdfb155959f9ec\", \"files\": {}}",
        "dest": "cargo/vendor/windows_x86_64_msvc-0.52.6",
        "dest-filename": ".cargo-checksum.json"
    },
    {
        "type": "archive",
        "archive-type": "tar-gzip",
        "url": "https://static.crates.io/crates/winnow/winnow-0.7.10.crate",
        "sha256": "c06928c8748d81b05c9be96aad92e1b6ff01833332f281e8cfca3be4b35fc9ec",
        "dest": "cargo/vendor/winnow-0.7.10"
    },
    {
        "type": "inline",
        "contents": "{\"package\": \"c06928c8748d81b05c9be96aad92e1b6ff01833332f281e8cfca3be4b35fc9ec\", \"files\": {}}",
        "dest": "cargo/vendor/winnow-0.7.10",
        "dest-filename": ".cargo-checksum.json"
    },
    {
        "type": "archive",
        "archive-type": "tar-gzip",
        "url": "https://static.crates.io/crates/zip/zip-4.3.0.crate",
        "sha256": "9aed4ac33e8eb078c89e6cbb1d5c4c7703ec6d299fc3e7c3695af8f8b423468b",
        "dest": "cargo/vendor/zip-4.3.0"
    },
    {
        "type": "inline",
        "contents": "{\"package\": \"9aed4ac33e8eb078c89e6cbb1d5c4c7703ec6d299fc3e7c3695af8f8b423468b\", \"files\": {}}",
        "dest": "cargo/vendor/zip-4.3.0",
        "dest-filename": ".cargo-checksum.json"
    },
    {
        "type": "archive",
        "archive-type": "tar-gzip",
        "url": "https://static.crates.io/crates/zlib-rs/zlib-rs-0.5.1.crate",
        "sha256": "626bd9fa9734751fc50d6060752170984d7053f5a39061f524cda68023d4db8a",
        "dest": "cargo/vendor/zlib-rs-0.5.1"
    },
    {
        "type": "inline",
        "contents": "{\"package\": \"626bd9fa9734751fc50d6060752170984d7053f5a39061f524cda68023d4db8a\", \"files\": {}}",
        "dest": "cargo/vendor/zlib-rs-0.5.1",
        "dest-filename": ".cargo-checksum.json"
    },
    {
        "type": "archive",
        "archive-type": "tar-gzip",
        "url": "https://static.crates.io/crates/zopfli/zopfli-0.8.1.crate",
        "sha256": "e5019f391bac5cf252e93bbcc53d039ffd62c7bfb7c150414d61369afe57e946",
        "dest": "cargo/vendor/zopfli-0.8.1"
    },
    {
        "type": "inline",
        "contents": "{\"package\": \"e5019f391bac5cf252e93bbcc53d039ffd62c7bfb7c150414d61369afe57e946\", \"files\": {}}",
        "dest": "cargo/vendor/zopfli-0.8.1",
        "dest-filename": ".cargo-checksum.json"
    },
    {
        "type": "inline",
        "contents": "[source.vendored-sources]\ndirectory = \"cargo/vendor\"\n\n[source.crates-io]\nreplace-with = \"vendored-sources\"\n",
        "dest": "cargo",
        "dest-filename": "config"
    }
]